[
  {
    "id": 1,
    "angles": {
      "25": 90.0,
      "26": 90.0,
      "27": 90.0,
      "28": 90.0,
      "29": 90.0,
      "30": 90.0,
      "31": 90.0,
      "32": 90.0,
      "33": 90.0,
      "34": 90.0,
      "35": 90.0,
      "36": 90.0,
      "37": 90.0,
      "38": 90.0,
      "39": 90.0,
      "40": 90.0,
      "41": 90.0,
      "42": 90.0,
      "43": 90.0,
      "44": 90.0,
      "45": 90.0,
      "46": 90.0,
      "47": 90.0,
      "48": 90.0,
      "49": 90.0,
      "50": 90.0,
      "51": 90.0,
      "52": 90.0,
      "53": 90.0,
      "54": 90.0,
      "7": 90,
      "8": 90,
      "9": 90,
      "10": 90,
      "11": 90,
      "12": 90,
      "13": 90,
      "14": 90,
      "15": 90,
      "16": 90,
      "17": 90,
      "18": 90,
      "19": 90,
      "20": 90,
      "21": 90,
      "22": 90,
      "23": 90,
      "24": 90,
      "1": 90,
      "2": 90,
      "3": 90,
      "4": 90,
      "5": 90,
      "6": 90
    }
  },
  {
    "id": 2,
    "angles": {
      "25": 100.4,
      "26": 100.4,
      "27": 100.4,
      "28": 100.4,
      "29": 100.4,
      "30": 100.4,
      "31": 100.4,
      "32": 100.4,
      "33": 100.4,
      "34": 100.4,
      "35": 100.4,
      "36": 100.4,
      "37": 100.4,
      "38": 100.4,
      "39": 100.4,
      "40": 100.4,
      "41": 100.4,
      "42": 100.4,
      "43": 100.4,
      "44": 100.4,
      "45": 100.4,
      "46": 100.4,
      "47": 100.4,
      "48": 100.4,
      "49": 100.4,
      "50": 100.4,
      "51": 100.4,
      "52": 100.4,
      "53": 100.4,
      "54": 100.4,
      "7": 90,
      "8": 90,
      "9": 90,
      "10": 90,
      "11": 90,
      "12": 90,
      "13": 90,
      "14": 90,
      "15": 90,
      "16": 90,
      "17": 90,
      "18": 90,
      "19": 90,
      "20": 90,
      "21": 90,
      "22": 90,
      "23": 90,
      "24": 90,
      "1": 90,
      "2": 90,
      "3": 90,
      "4": 90,
      "5": 90,
      "6": 90
    }
  },
  {
    "id": 3,
    "angles": {
      "25": 110.0,
      "26": 110.0,
      "27": 110.0,
      "28": 110.0,
      "29": 110.0,
      "30": 110.0,
      "31": 110.0,
      "32": 110.0,
      "33": 110.0,
      "34": 110.0,
      "35": 110.0,
      "36": 110.0,
      "37": 110.0,
      "38": 110.0,
      "39": 110.0,
      "40": 110.0,
      "41": 110.0,
      "42": 110.0,
      "43": 110.0,
      "44": 110.0,
      "45": 110.0,
      "46": 110.0,
      "47": 110.0,
      "48": 110.0,
      "49": 110.0,
      "50": 110.0,
      "51": 110.0,
      "52": 110.0,
      "53": 110.0,
      "54": 110.0,
      "7": 90,
      "8": 90,
      "9": 90,
      "10": 90,
      "11": 90,
      "12": 90,
      "13": 90,
      "14": 90,
      "15": 90,
      "16": 90,
      "17": 90,
      "18": 90,
      "19": 90,
      "20": 90,
      "21": 90,
      "22": 90,
      "23": 90,
      "24": 90,
      "1": 90,
      "2": 90,
      "3": 90,
      "4": 90,
      "5": 90,
      "6": 90
    }
  },
  {
    "id": 4,
    "angles": {
      "25": 118.3,
      "26": 118.3,
      "27": 118.3,
      "28": 118.3,
      "29": 118.3,
      "30": 118.3,
      "31": 118.3,
      "32": 118.3,
      "33": 118.3,
      "34": 118.3,
      "35": 118.3,
      "36": 118.3,
      "37": 118.3,
      "38": 118.3,
      "39": 118.3,
      "40": 118.3,
      "41": 118.3,
      "42": 118.3,
      "43": 118.3,
      "44": 118.3,
      "45": 118.3,
      "46": 118.3,
      "47": 118.3,
      "48": 118.3,
      "49": 118.3,
      "50": 118.3,
      "51": 118.3,
      "52": 118.3,
      "53": 118.3,
      "54": 118.3,
      "7": 90,
      "8": 90,
      "9": 90,
      "10": 90,
      "11": 90,
      "12": 90,
      "13": 90,
      "14": 90,
      "15": 90,
      "16": 90,
      "17": 90,
      "18": 90,
      "19": 90,
      "20": 90,
      "21": 90,
      "22": 90,
      "23": 90,
      "24": 90,
      "1": 90,
      "2": 90,
      "3": 90,
      "4": 90,
      "5": 90,
      "6": 90
    }
  },
  {
    "id": 5,
    "angles": {
      "25": 124.6,
      "26": 124.6,
      "27": 124.6,
      "28": 124.6,
      "29": 124.6,
      "30": 124.6,
      "31": 124.6,
      "32": 124.6,
      "33": 124.6,
      "34": 124.6,
      "35": 124.6,
      "36": 124.6,
      "37": 124.6,
      "38": 124.6,
      "39": 124.6,
      "40": 124.6,
      "41": 124.6,
      "42": 124.6,
      "43": 124.6,
      "44": 124.6,
      "45": 124.6,
      "46": 124.6,
      "47": 124.6,
      "48": 124.6,
      "49": 124.6,
      "50": 124.6,
      "51": 124.6,
      "52": 124.6,
      "53": 124.6,
      "54": 124.6,
      "7": 90,
      "8": 90,
      "9": 90,
      "10": 90,
      "11": 90,
      "12": 90,
      "13": 90,
      "14": 90,
      "15": 90,
      "16": 90,
      "17": 90,
      "18": 90,
      "19": 90,
      "20": 90,
      "21": 90,
      "22": 90,
      "23": 90,
      "24": 90,
      "1": 90,
      "2": 90,
      "3": 90,
      "4": 90,
      "5": 90,
      "6": 90
    }
  },
  {
    "id": 6,
    "angles": {
      "25": 128.6,
      "26": 128.6,
      "27": 128.6,
      "28": 128.6,
      "29": 128.6,
      "30": 128.6,
      "31": 128.6,
      "32": 128.6,
      "33": 128.6,
      "34": 128.6,
      "35": 128.6,
      "36": 128.6,
      "37": 128.6,
      "38": 128.6,
      "39": 128.6,
      "40": 128.6,
      "41": 128.6,
      "42": 128.6,
      "43": 128.6,
      "44": 128.6,
      "45": 128.6,
      "46": 128.6,
      "47": 128.6,
      "48": 128.6,
      "49": 128.6,
      "50": 128.6,
      "51": 128.6,
      "52": 128.6,
      "53": 128.6,
      "54": 128.6,
      "7": 90,
      "8": 90,
      "9": 90,
      "10": 90,
      "11": 90,
      "12": 90,
      "13": 90,
      "14": 90,
      "15": 90,
      "16": 90,
      "17": 90,
      "18": 90,
      "19": 90,
      "20": 90,
      "21": 90,
      "22": 90,
      "23": 90,
      "24": 90,
      "1": 90,
      "2": 90,
      "3": 90,
      "4": 90,
      "5": 90,
      "6": 90
    }
  },
  {
    "id": 7,
    "angles": {
      "25": 130.0,
      "26": 130.0,
      "27": 130.0,
      "28": 130.0,
      "29": 130.0,
      "30": 130.0,
      "31": 130.0,
      "32": 130.0,
      "33": 130.0,
      "34": 130.0,
      "35": 130.0,
      "36": 130.0,
      "37": 130.0,
      "38": 130.0,
      "39": 130.0,
      "40": 130.0,
      "41": 130.0,
      "42": 130.0,
      "43": 130.0,
      "44": 130.0,
      "45": 130.0,
      "46": 130.0,
      "47": 130.0,
      "48": 130.0,
      "49": 130.0,
      "50": 130.0,
      "51": 130.0,
      "52": 130.0,
      "53": 130.0,
      "54": 130.0,
      "7": 90,
      "8": 90,
      "9": 90,
      "10": 90,
      "11": 90,
      "12": 90,
      "13": 90,
      "14": 90,
      "15": 90,
      "16": 90,
      "17": 90,
      "18": 90,
      "19": 90,
      "20": 90,
      "21": 90,
      "22": 90,
      "23": 90,
      "24": 90,
      "1": 90,
      "2": 90,
      "3": 90,
      "4": 90,
      "5": 90,
      "6": 90
    }
  },
  {
    "id": 8,
    "angles": {
      "25": 128.6,
      "26": 128.6,
      "27": 128.6,
      "28": 128.6,
      "29": 128.6,
      "30": 128.6,
      "31": 128.6,
      "32": 128.6,
      "33": 128.6,
      "34": 128.6,
      "35": 128.6,
      "36": 128.6,
      "37": 128.6,
      "38": 128.6,
      "39": 128.6,
      "40": 128.6,
      "41": 128.6,
      "42": 128.6,
      "43": 128.6,
      "44": 128.6,
      "45": 128.6,
      "46": 128.6,
      "47": 128.6,
      "48": 128.6,
      "49": 128.6,
      "50": 128.6,
      "51": 128.6,
      "52": 128.6,
      "53": 128.6,
      "54": 128.6,
      "7": 90,
      "8": 90,
      "9": 90,
      "10": 90,
      "11": 90,
      "12": 90,
      "13": 90,
      "14": 90,
      "15": 90,
      "16": 90,
      "17": 90,
      "18": 90,
      "19": 90,
      "20": 90,
      "21": 90,
      "22": 90,
      "23": 90,
      "24": 90,
      "1": 90,
      "2": 90,
      "3": 90,
      "4": 90,
      "5": 90,
      "6": 90
    }
  },
  {
    "id": 9,
    "angles": {
      "25": 124.6,
      "26": 124.6,
      "27": 124.6,
      "28": 124.6,
      "29": 124.6,
      "30": 124.6,
      "31": 124.6,
      "32": 124.6,
      "33": 124.6,
      "34": 124.6,
      "35": 124.6,
      "36": 124.6,
      "37": 124.6,
      "38": 124.6,
      "39": 124.6,
      "40": 124.6,
      "41": 124.6,
      "42": 124.6,
      "43": 124.6,
      "44": 124.6,
      "45": 124.6,
      "46": 124.6,
      "47": 124.6,
      "48": 124.6,
      "49": 124.6,
      "50": 124.6,
      "51": 124.6,
      "52": 124.6,
      "53": 124.6,
      "54": 124.6,
      "7": 90,
      "8": 90,
      "9": 90,
      "10": 90,
      "11": 90,
      "12": 90,
      "13": 90,
      "14": 90,
      "15": 90,
      "16": 90,
      "17": 90,
      "18": 90,
      "19": 90,
      "20": 90,
      "21": 90,
      "22": 90,
      "23": 90,
      "24": 90,
      "1": 90,
      "2": 90,
      "3": 90,
      "4": 90,
      "5": 90,
      "6": 90
    }
  },
  {
    "id": 10,
    "angles": {
      "25": 118.3,
      "26": 118.3,
      "27": 118.3,
      "28": 118.3,
      "29": 118.3,
      "30": 118.3,
      "31": 118.3,
      "32": 118.3,
      "33": 118.3,
      "34": 118.3,
      "35": 118.3,
      "36": 118.3,
      "37": 118.3,
      "38": 118.3,
      "39": 118.3,
      "40": 118.3,
      "41": 118.3,
      "42": 118.3,
      "43": 118.3,
      "44": 118.3,
      "45": 118.3,
      "46": 118.3,
      "47": 118.3,
      "48": 118.3,
      "49": 118.3,
      "50": 118.3,
      "51": 118.3,
      "52": 118.3,
      "53": 118.3,
      "54": 118.3,
      "7": 90,
      "8": 90,
      "9": 90,
      "10": 90,
      "11": 90,
      "12": 90,
      "13": 90,
      "14": 90,
      "15": 90,
      "16": 90,
      "17": 90,
      "18": 90,
      "19": 90,
      "20": 90,
      "21": 90,
      "22": 90,
      "23": 90,
      "24": 90,
      "1": 90,
      "2": 90,
      "3": 90,
      "4": 90,
      "5": 90,
      "6": 90
    }
  },
  {
    "id": 11,
    "angles": {
      "25": 110.0,
      "26": 110.0,
      "27": 110.0,
      "28": 110.0,
      "29": 110.0,
      "30": 110.0,
      "31": 110.0,
      "32": 110.0,
      "33": 110.0,
      "34": 110.0,
      "35": 110.0,
      "36": 110.0,
      "37": 110.0,
      "38": 110.0,
      "39": 110.0,
      "40": 110.0,
      "41": 110.0,
      "42": 110.0,
      "43": 110.0,
      "44": 110.0,
      "45": 110.0,
      "46": 110.0,
      "47": 110.0,
      "48": 110.0,
      "49": 110.0,
      "50": 110.0,
      "51": 110.0,
      "52": 110.0,
      "53": 110.0,
      "54": 110.0,
      "7": 90,
      "8": 90,
      "9": 90,
      "10": 90,
      "11": 90,
      "12": 90,
      "13": 90,
      "14": 90,
      "15": 90,
      "16": 90,
      "17": 90,
      "18": 90,
      "19": 90,
      "20": 90,
      "21": 90,
      "22": 90,
      "23": 90,
      "24": 90,
      "1": 90,
      "2": 90,
      "3": 90,
      "4": 90,
      "5": 90,
      "6": 90
    }
  },
  {
    "id": 12,
    "angles": {
      "25": 100.4,
      "26": 100.4,
      "27": 100.4,
      "28": 100.4,
      "29": 100.4,
      "30": 100.4,
      "31": 100.4,
      "32": 100.4,
      "33": 100.4,
      "34": 100.4,
      "35": 100.4,
      "36": 100.4,
      "37": 100.4,
      "38": 100.4,
      "39": 100.4,
      "40": 100.4,
      "41": 100.4,
      "42": 100.4,
      "43": 100.4,
      "44": 100.4,
      "45": 100.4,
      "46": 100.4,
      "47": 100.4,
      "48": 100.4,
      "49": 100.4,
      "50": 100.4,
      "51": 100.4,
      "52": 100.4,
      "53": 100.4,
      "54": 100.4,
      "7": 90,
      "8": 90,
      "9": 90,
      "10": 90,
      "11": 90,
      "12": 90,
      "13": 90,
      "14": 90,
      "15": 90,
      "16": 90,
      "17": 90,
      "18": 90,
      "19": 90,
      "20": 90,
      "21": 90,
      "22": 90,
      "23": 90,
      "24": 90,
      "1": 90,
      "2": 90,
      "3": 90,
      "4": 90,
      "5": 90,
      "6": 90
    }
  },
  {
    "id": 13,
    "angles": {
      "25": 90.0,
      "26": 90.0,
      "27": 90.0,
      "28": 90.0,
      "29": 90.0,
      "30": 90.0,
      "31": 90.0,
      "32": 90.0,
      "33": 90.0,
      "34": 90.0,
      "35": 90.0,
      "36": 90.0,
      "37": 90.0,
      "38": 90.0,
      "39": 90.0,
      "40": 90.0,
      "41": 90.0,
      "42": 90.0,
      "43": 90.0,
      "44": 90.0,
      "45": 90.0,
      "46": 90.0,
      "47": 90.0,
      "48": 90.0,
      "49": 90.0,
      "50": 90.0,
      "51": 90.0,
      "52": 90.0,
      "53": 90.0,
      "54": 90.0,
      "7": 90.0,
      "8": 90.0,
      "9": 90.0,
      "10": 90.0,
      "11": 90.0,
      "12": 90.0,
      "13": 90.0,
      "14": 90.0,
      "15": 90.0,
      "16": 90.0,
      "17": 90.0,
      "18": 90.0,
      "19": 90.0,
      "20": 90.0,
      "21": 90.0,
      "22": 90.0,
      "23": 90.0,
      "24": 90.0,
      "1": 90,
      "2": 90,
      "3": 90,
      "4": 90,
      "5": 90,
      "6": 90
    }
  },
  {
    "id": 14,
    "angles": {
      "25": 79.6,
      "26": 79.6,
      "27": 79.6,
      "28": 79.6,
      "29": 79.6,
      "30": 79.6,
      "31": 79.6,
      "32": 79.6,
      "33": 79.6,
      "34": 79.6,
      "35": 79.6,
      "36": 79.6,
      "37": 79.6,
      "38": 79.6,
      "39": 79.6,
      "40": 79.6,
      "41": 79.6,
      "42": 79.6,
      "43": 79.6,
      "44": 79.6,
      "45": 79.6,
      "46": 79.6,
      "47": 79.6,
      "48": 79.6,
      "49": 79.6,
      "50": 79.6,
      "51": 79.6,
      "52": 79.6,
      "53": 79.6,
      "54": 79.6,
      "7": 100.4,
      "8": 100.4,
      "9": 100.4,
      "10": 100.4,
      "11": 100.4,
      "12": 100.4,
      "13": 100.4,
      "14": 100.4,
      "15": 100.4,
      "16": 100.4,
      "17": 100.4,
      "18": 100.4,
      "19": 100.4,
      "20": 100.4,
      "21": 100.4,
      "22": 100.4,
      "23": 100.4,
      "24": 100.4,
      "1": 90,
      "2": 90,
      "3": 90,
      "4": 90,
      "5": 90,
      "6": 90
    }
  },
  {
    "id": 15,
    "angles": {
      "25": 70.0,
      "26": 70.0,
      "27": 70.0,
      "28": 70.0,
      "29": 70.0,
      "30": 70.0,
      "31": 70.0,
      "32": 70.0,
      "33": 70.0,
      "34": 70.0,
      "35": 70.0,
      "36": 70.0,
      "37": 70.0,
      "38": 70.0,
      "39": 70.0,
      "40": 70.0,
      "41": 70.0,
      "42": 70.0,
      "43": 70.0,
      "44": 70.0,
      "45": 70.0,
      "46": 70.0,
      "47": 70.0,
      "48": 70.0,
      "49": 70.0,
      "50": 70.0,
      "51": 70.0,
      "52": 70.0,
      "53": 70.0,
      "54": 70.0,
      "7": 110.0,
      "8": 110.0,
      "9": 110.0,
      "10": 110.0,
      "11": 110.0,
      "12": 110.0,
      "13": 110.0,
      "14": 110.0,
      "15": 110.0,
      "16": 110.0,
      "17": 110.0,
      "18": 110.0,
      "19": 110.0,
      "20": 110.0,
      "21": 110.0,
      "22": 110.0,
      "23": 110.0,
      "24": 110.0,
      "1": 90,
      "2": 90,
      "3": 90,
      "4": 90,
      "5": 90,
      "6": 90
    }
  },
  {
    "id": 16,
    "angles": {
      "25": 61.7,
      "26": 61.7,
      "27": 61.7,
      "28": 61.7,
      "29": 61.7,
      "30": 61.7,
      "31": 61.7,
      "32": 61.7,
      "33": 61.7,
      "34": 61.7,
      "35": 61.7,
      "36": 61.7,
      "37": 61.7,
      "38": 61.7,
      "39": 61.7,
      "40": 61.7,
      "41": 61.7,
      "42": 61.7,
      "43": 61.7,
      "44": 61.7,
      "45": 61.7,
      "46": 61.7,
      "47": 61.7,
      "48": 61.7,
      "49": 61.7,
      "50": 61.7,
      "51": 61.7,
      "52": 61.7,
      "53": 61.7,
      "54": 61.7,
      "7": 118.3,
      "8": 118.3,
      "9": 118.3,
      "10": 118.3,
      "11": 118.3,
      "12": 118.3,
      "13": 118.3,
      "14": 118.3,
      "15": 118.3,
      "16": 118.3,
      "17": 118.3,
      "18": 118.3,
      "19": 118.3,
      "20": 118.3,
      "21": 118.3,
      "22": 118.3,
      "23": 118.3,
      "24": 118.3,
      "1": 90,
      "2": 90,
      "3": 90,
      "4": 90,
      "5": 90,
      "6": 90
    }
  },
  {
    "id": 17,
    "angles": {
      "25": 55.4,
      "26": 55.4,
      "27": 55.4,
      "28": 55.4,
      "29": 55.4,
      "30": 55.4,
      "31": 55.4,
      "32": 55.4,
      "33": 55.4,
      "34": 55.4,
      "35": 55.4,
      "36": 55.4,
      "37": 55.4,
      "38": 55.4,
      "39": 55.4,
      "40": 55.4,
      "41": 55.4,
      "42": 55.4,
      "43": 55.4,
      "44": 55.4,
      "45": 55.4,
      "46": 55.4,
      "47": 55.4,
      "48": 55.4,
      "49": 55.4,
      "50": 55.4,
      "51": 55.4,
      "52": 55.4,
      "53": 55.4,
      "54": 55.4,
      "7": 124.6,
      "8": 124.6,
      "9": 124.6,
      "10": 124.6,
      "11": 124.6,
      "12": 124.6,
      "13": 124.6,
      "14": 124.6,
      "15": 124.6,
      "16": 124.6,
      "17": 124.6,
      "18": 124.6,
      "19": 124.6,
      "20": 124.6,
      "21": 124.6,
      "22": 124.6,
      "23": 124.6,
      "24": 124.6,
      "1": 90,
      "2": 90,
      "3": 90,
      "4": 90,
      "5": 90,
      "6": 90
    }
  },
  {
    "id": 18,
    "angles": {
      "25": 51.4,
      "26": 51.4,
      "27": 51.4,
      "28": 51.4,
      "29": 51.4,
      "30": 51.4,
      "31": 51.4,
      "32": 51.4,
      "33": 51.4,
      "34": 51.4,
      "35": 51.4,
      "36": 51.4,
      "37": 51.4,
      "38": 51.4,
      "39": 51.4,
      "40": 51.4,
      "41": 51.4,
      "42": 51.4,
      "43": 51.4,
      "44": 51.4,
      "45": 51.4,
      "46": 51.4,
      "47": 51.4,
      "48": 51.4,
      "49": 51.4,
      "50": 51.4,
      "51": 51.4,
      "52": 51.4,
      "53": 51.4,
      "54": 51.4,
      "7": 128.6,
      "8": 128.6,
      "9": 128.6,
      "10": 128.6,
      "11": 128.6,
      "12": 128.6,
      "13": 128.6,
      "14": 128.6,
      "15": 128.6,
      "16": 128.6,
      "17": 128.6,
      "18": 128.6,
      "19": 128.6,
      "20": 128.6,
      "21": 128.6,
      "22": 128.6,
      "23": 128.6,
      "24": 128.6,
      "1": 90,
      "2": 90,
      "3": 90,
      "4": 90,
      "5": 90,
      "6": 90
    }
  },
  {
    "id": 19,
    "angles": {
      "25": 50.0,
      "26": 50.0,
      "27": 50.0,
      "28": 50.0,
      "29": 50.0,
      "30": 50.0,
      "31": 50.0,
      "32": 50.0,
      "33": 50.0,
      "34": 50.0,
      "35": 50.0,
      "36": 50.0,
      "37": 50.0,
      "38": 50.0,
      "39": 50.0,
      "40": 50.0,
      "41": 50.0,
      "42": 50.0,
      "43": 50.0,
      "44": 50.0,
      "45": 50.0,
      "46": 50.0,
      "47": 50.0,
      "48": 50.0,
      "49": 50.0,
      "50": 50.0,
      "51": 50.0,
      "52": 50.0,
      "53": 50.0,
      "54": 50.0,
      "7": 130.0,
      "8": 130.0,
      "9": 130.0,
      "10": 130.0,
      "11": 130.0,
      "12": 130.0,
      "13": 130.0,
      "14": 130.0,
      "15": 130.0,
      "16": 130.0,
      "17": 130.0,
      "18": 130.0,
      "19": 130.0,
      "20": 130.0,
      "21": 130.0,
      "22": 130.0,
      "23": 130.0,
      "24": 130.0,
      "1": 90,
      "2": 90,
      "3": 90,
      "4": 90,
      "5": 90,
      "6": 90
    }
  },
  {
    "id": 20,
    "angles": {
      "25": 51.4,
      "26": 51.4,
      "27": 51.4,
      "28": 51.4,
      "29": 51.4,
      "30": 51.4,
      "31": 51.4,
      "32": 51.4,
      "33": 51.4,
      "34": 51.4,
      "35": 51.4,
      "36": 51.4,
      "37": 51.4,
      "38": 51.4,
      "39": 51.4,
      "40": 51.4,
      "41": 51.4,
      "42": 51.4,
      "43": 51.4,
      "44": 51.4,
      "45": 51.4,
      "46": 51.4,
      "47": 51.4,
      "48": 51.4,
      "49": 51.4,
      "50": 51.4,
      "51": 51.4,
      "52": 51.4,
      "53": 51.4,
      "54": 51.4,
      "7": 128.6,
      "8": 128.6,
      "9": 128.6,
      "10": 128.6,
      "11": 128.6,
      "12": 128.6,
      "13": 128.6,
      "14": 128.6,
      "15": 128.6,
      "16": 128.6,
      "17": 128.6,
      "18": 128.6,
      "19": 128.6,
      "20": 128.6,
      "21": 128.6,
      "22": 128.6,
      "23": 128.6,
      "24": 128.6,
      "1": 90,
      "2": 90,
      "3": 90,
      "4": 90,
      "5": 90,
      "6": 90
    }
  },
  {
    "id": 21,
    "angles": {
      "25": 55.4,
      "26": 55.4,
      "27": 55.4,
      "28": 55.4,
      "29": 55.4,
      "30": 55.4,
      "31": 55.4,
      "32": 55.4,
      "33": 55.4,
      "34": 55.4,
      "35": 55.4,
      "36": 55.4,
      "37": 55.4,
      "38": 55.4,
      "39": 55.4,
      "40": 55.4,
      "41": 55.4,
      "42": 55.4,
      "43": 55.4,
      "44": 55.4,
      "45": 55.4,
      "46": 55.4,
      "47": 55.4,
      "48": 55.4,
      "49": 55.4,
      "50": 55.4,
      "51": 55.4,
      "52": 55.4,
      "53": 55.4,
      "54": 55.4,
      "7": 124.6,
      "8": 124.6,
      "9": 124.6,
      "10": 124.6,
      "11": 124.6,
      "12": 124.6,
      "13": 124.6,
      "14": 124.6,
      "15": 124.6,
      "16": 124.6,
      "17": 124.6,
      "18": 124.6,
      "19": 124.6,
      "20": 124.6,
      "21": 124.6,
      "22": 124.6,
      "23": 124.6,
      "24": 124.6,
      "1": 90,
      "2": 90,
      "3": 90,
      "4": 90,
      "5": 90,
      "6": 90
    }
  },
  {
    "id": 22,
    "angles": {
      "25": 61.7,
      "26": 61.7,
      "27": 61.7,
      "28": 61.7,
      "29": 61.7,
      "30": 61.7,
      "31": 61.7,
      "32": 61.7,
      "33": 61.7,
      "34": 61.7,
      "35": 61.7,
      "36": 61.7,
      "37": 61.7,
      "38": 61.7,
      "39": 61.7,
      "40": 61.7,
      "41": 61.7,
      "42": 61.7,
      "43": 61.7,
      "44": 61.7,
      "45": 61.7,
      "46": 61.7,
      "47": 61.7,
      "48": 61.7,
      "49": 61.7,
      "50": 61.7,
      "51": 61.7,
      "52": 61.7,
      "53": 61.7,
      "54": 61.7,
      "7": 118.3,
      "8": 118.3,
      "9": 118.3,
      "10": 118.3,
      "11": 118.3,
      "12": 118.3,
      "13": 118.3,
      "14": 118.3,
      "15": 118.3,
      "16": 118.3,
      "17": 118.3,
      "18": 118.3,
      "19": 118.3,
      "20": 118.3,
      "21": 118.3,
      "22": 118.3,
      "23": 118.3,
      "24": 118.3,
      "1": 90,
      "2": 90,
      "3": 90,
      "4": 90,
      "5": 90,
      "6": 90
    }
  },
  {
    "id": 23,
    "angles": {
      "25": 70.0,
      "26": 70.0,
      "27": 70.0,
      "28": 70.0,
      "29": 70.0,
      "30": 70.0,
      "31": 70.0,
      "32": 70.0,
      "33": 70.0,
      "34": 70.0,
      "35": 70.0,
      "36": 70.0,
      "37": 70.0,
      "38": 70.0,
      "39": 70.0,
      "40": 70.0,
      "41": 70.0,
      "42": 70.0,
      "43": 70.0,
      "44": 70.0,
      "45": 70.0,
      "46": 70.0,
      "47": 70.0,
      "48": 70.0,
      "49": 70.0,
      "50": 70.0,
      "51": 70.0,
      "52": 70.0,
      "53": 70.0,
      "54": 70.0,
      "7": 110.0,
      "8": 110.0,
      "9": 110.0,
      "10": 110.0,
      "11": 110.0,
      "12": 110.0,
      "13": 110.0,
      "14": 110.0,
      "15": 110.0,
      "16": 110.0,
      "17": 110.0,
      "18": 110.0,
      "19": 110.0,
      "20": 110.0,
      "21": 110.0,
      "22": 110.0,
      "23": 110.0,
      "24": 110.0,
      "1": 90,
      "2": 90,
      "3": 90,
      "4": 90,
      "5": 90,
      "6": 90
    }
  },
  {
    "id": 24,
    "angles": {
      "25": 79.6,
      "26": 79.6,
      "27": 79.6,
      "28": 79.6,
      "29": 79.6,
      "30": 79.6,
      "31": 79.6,
      "32": 79.6,
      "33": 79.6,
      "34": 79.6,
      "35": 79.6,
      "36": 79.6,
      "37": 79.6,
      "38": 79.6,
      "39": 79.6,
      "40": 79.6,
      "41": 79.6,
      "42": 79.6,
      "43": 79.6,
      "44": 79.6,
      "45": 79.6,
      "46": 79.6,
      "47": 79.6,
      "48": 79.6,
      "49": 79.6,
      "50": 79.6,
      "51": 79.6,
      "52": 79.6,
      "53": 79.6,
      "54": 79.6,
      "7": 100.4,
      "8": 100.4,
      "9": 100.4,
      "10": 100.4,
      "11": 100.4,
      "12": 100.4,
      "13": 100.4,
      "14": 100.4,
      "15": 100.4,
      "16": 100.4,
      "17": 100.4,
      "18": 100.4,
      "19": 100.4,
      "20": 100.4,
      "21": 100.4,
      "22": 100.4,
      "23": 100.4,
      "24": 100.4,
      "1": 90,
      "2": 90,
      "3": 90,
      "4": 90,
      "5": 90,
      "6": 90
    }
  },
  {
    "id": 25,
    "angles": {
      "25": 90.0,
      "26": 90.0,
      "27": 90.0,
      "28": 90.0,
      "29": 90.0,
      "30": 90.0,
      "31": 90.0,
      "32": 90.0,
      "33": 90.0,
      "34": 90.0,
      "35": 90.0,
      "36": 90.0,
      "37": 90.0,
      "38": 90.0,
      "39": 90.0,
      "40": 90.0,
      "41": 90.0,
      "42": 90.0,
      "43": 90.0,
      "44": 90.0,
      "45": 90.0,
      "46": 90.0,
      "47": 90.0,
      "48": 90.0,
      "49": 90.0,
      "50": 90.0,
      "51": 90.0,
      "52": 90.0,
      "53": 90.0,
      "54": 90.0,
      "7": 90.0,
      "8": 90.0,
      "9": 90.0,
      "10": 90.0,
      "11": 90.0,
      "12": 90.0,
      "13": 90.0,
      "14": 90.0,
      "15": 90.0,
      "16": 90.0,
      "17": 90.0,
      "18": 90.0,
      "19": 90.0,
      "20": 90.0,
      "21": 90.0,
      "22": 90.0,
      "23": 90.0,
      "24": 90.0,
      "1": 90.0,
      "2": 90.0,
      "3": 90.0,
      "4": 90.0,
      "5": 90.0,
      "6": 90.0
    }
  },
  {
    "id": 26,
    "angles": {
      "25": 100.4,
      "26": 100.4,
      "27": 100.4,
      "28": 100.4,
      "29": 100.4,
      "30": 100.4,
      "31": 100.4,
      "32": 100.4,
      "33": 100.4,
      "34": 100.4,
      "35": 100.4,
      "36": 100.4,
      "37": 100.4,
      "38": 100.4,
      "39": 100.4,
      "40": 100.4,
      "41": 100.4,
      "42": 100.4,
      "43": 100.4,
      "44": 100.4,
      "45": 100.4,
      "46": 100.4,
      "47": 100.4,
      "48": 100.4,
      "49": 100.4,
      "50": 100.4,
      "51": 100.4,
      "52": 100.4,
      "53": 100.4,
      "54": 100.4,
      "7": 79.6,
      "8": 79.6,
      "9": 79.6,
      "10": 79.6,
      "11": 79.6,
      "12": 79.6,
      "13": 79.6,
      "14": 79.6,
      "15": 79.6,
      "16": 79.6,
      "17": 79.6,
      "18": 79.6,
      "19": 79.6,
      "20": 79.6,
      "21": 79.6,
      "22": 79.6,
      "23": 79.6,
      "24": 79.6,
      "1": 100.4,
      "2": 100.4,
      "3": 100.4,
      "4": 100.4,
      "5": 100.4,
      "6": 100.4
    }
  },
  {
    "id": 27,
    "angles": {
      "25": 110.0,
      "26": 110.0,
      "27": 110.0,
      "28": 110.0,
      "29": 110.0,
      "30": 110.0,
      "31": 110.0,
      "32": 110.0,
      "33": 110.0,
      "34": 110.0,
      "35": 110.0,
      "36": 110.0,
      "37": 110.0,
      "38": 110.0,
      "39": 110.0,
      "40": 110.0,
      "41": 110.0,
      "42": 110.0,
      "43": 110.0,
      "44": 110.0,
      "45": 110.0,
      "46": 110.0,
      "47": 110.0,
      "48": 110.0,
      "49": 110.0,
      "50": 110.0,
      "51": 110.0,
      "52": 110.0,
      "53": 110.0,
      "54": 110.0,
      "7": 70.0,
      "8": 70.0,
      "9": 70.0,
      "10": 70.0,
      "11": 70.0,
      "12": 70.0,
      "13": 70.0,
      "14": 70.0,
      "15": 70.0,
      "16": 70.0,
      "17": 70.0,
      "18": 70.0,
      "19": 70.0,
      "20": 70.0,
      "21": 70.0,
      "22": 70.0,
      "23": 70.0,
      "24": 70.0,
      "1": 110.0,
      "2": 110.0,
      "3": 110.0,
      "4": 110.0,
      "5": 110.0,
      "6": 110.0
    }
  },
  {
    "id": 28,
    "angles": {
      "25": 118.3,
      "26": 118.3,
      "27": 118.3,
      "28": 118.3,
      "29": 118.3,
      "30": 118.3,
      "31": 118.3,
      "32": 118.3,
      "33": 118.3,
      "34": 118.3,
      "35": 118.3,
      "36": 118.3,
      "37": 118.3,
      "38": 118.3,
      "39": 118.3,
      "40": 118.3,
      "41": 118.3,
      "42": 118.3,
      "43": 118.3,
      "44": 118.3,
      "45": 118.3,
      "46": 118.3,
      "47": 118.3,
      "48": 118.3,
      "49": 118.3,
      "50": 118.3,
      "51": 118.3,
      "52": 118.3,
      "53": 118.3,
      "54": 118.3,
      "7": 61.7,
      "8": 61.7,
      "9": 61.7,
      "10": 61.7,
      "11": 61.7,
      "12": 61.7,
      "13": 61.7,
      "14": 61.7,
      "15": 61.7,
      "16": 61.7,
      "17": 61.7,
      "18": 61.7,
      "19": 61.7,
      "20": 61.7,
      "21": 61.7,
      "22": 61.7,
      "23": 61.7,
      "24": 61.7,
      "1": 118.3,
      "2": 118.3,
      "3": 118.3,
      "4": 118.3,
      "5": 118.3,
      "6": 118.3
    }
  },
  {
    "id": 29,
    "angles": {
      "25": 124.6,
      "26": 124.6,
      "27": 124.6,
      "28": 124.6,
      "29": 124.6,
      "30": 124.6,
      "31": 124.6,
      "32": 124.6,
      "33": 124.6,
      "34": 124.6,
      "35": 124.6,
      "36": 124.6,
      "37": 124.6,
      "38": 124.6,
      "39": 124.6,
      "40": 124.6,
      "41": 124.6,
      "42": 124.6,
      "43": 124.6,
      "44": 124.6,
      "45": 124.6,
      "46": 124.6,
      "47": 124.6,
      "48": 124.6,
      "49": 124.6,
      "50": 124.6,
      "51": 124.6,
      "52": 124.6,
      "53": 124.6,
      "54": 124.6,
      "7": 55.4,
      "8": 55.4,
      "9": 55.4,
      "10": 55.4,
      "11": 55.4,
      "12": 55.4,
      "13": 55.4,
      "14": 55.4,
      "15": 55.4,
      "16": 55.4,
      "17": 55.4,
      "18": 55.4,
      "19": 55.4,
      "20": 55.4,
      "21": 55.4,
      "22": 55.4,
      "23": 55.4,
      "24": 55.4,
      "1": 124.6,
      "2": 124.6,
      "3": 124.6,
      "4": 124.6,
      "5": 124.6,
      "6": 124.6
    }
  },
  {
    "id": 30,
    "angles": {
      "25": 128.6,
      "26": 128.6,
      "27": 128.6,
      "28": 128.6,
      "29": 128.6,
      "30": 128.6,
      "31": 128.6,
      "32": 128.6,
      "33": 128.6,
      "34": 128.6,
      "35": 128.6,
      "36": 128.6,
      "37": 128.6,
      "38": 128.6,
      "39": 128.6,
      "40": 128.6,
      "41": 128.6,
      "42": 128.6,
      "43": 128.6,
      "44": 128.6,
      "45": 128.6,
      "46": 128.6,
      "47": 128.6,
      "48": 128.6,
      "49": 128.6,
      "50": 128.6,
      "51": 128.6,
      "52": 128.6,
      "53": 128.6,
      "54": 128.6,
      "7": 51.4,
      "8": 51.4,
      "9": 51.4,
      "10": 51.4,
      "11": 51.4,
      "12": 51.4,
      "13": 51.4,
      "14": 51.4,
      "15": 51.4,
      "16": 51.4,
      "17": 51.4,
      "18": 51.4,
      "19": 51.4,
      "20": 51.4,
      "21": 51.4,
      "22": 51.4,
      "23": 51.4,
      "24": 51.4,
      "1": 128.6,
      "2": 128.6,
      "3": 128.6,
      "4": 128.6,
      "5": 128.6,
      "6": 128.6
    }
  },
  {
    "id": 31,
    "angles": {
      "25": 130.0,
      "26": 130.0,
      "27": 130.0,
      "28": 130.0,
      "29": 130.0,
      "30": 130.0,
      "31": 130.0,
      "32": 130.0,
      "33": 130.0,
      "34": 130.0,
      "35": 130.0,
      "36": 130.0,
      "37": 130.0,
      "38": 130.0,
      "39": 130.0,
      "40": 130.0,
      "41": 130.0,
      "42": 130.0,
      "43": 130.0,
      "44": 130.0,
      "45": 130.0,
      "46": 130.0,
      "47": 130.0,
      "48": 130.0,
      "49": 130.0,
      "50": 130.0,
      "51": 130.0,
      "52": 130.0,
      "53": 130.0,
      "54": 130.0,
      "7": 50.0,
      "8": 50.0,
      "9": 50.0,
      "10": 50.0,
      "11": 50.0,
      "12": 50.0,
      "13": 50.0,
      "14": 50.0,
      "15": 50.0,
      "16": 50.0,
      "17": 50.0,
      "18": 50.0,
      "19": 50.0,
      "20": 50.0,
      "21": 50.0,
      "22": 50.0,
      "23": 50.0,
      "24": 50.0,
      "1": 130.0,
      "2": 130.0,
      "3": 130.0,
      "4": 130.0,
      "5": 130.0,
      "6": 130.0
    }
  },
  {
    "id": 32,
    "angles": {
      "25": 128.6,
      "26": 128.6,
      "27": 128.6,
      "28": 128.6,
      "29": 128.6,
      "30": 128.6,
      "31": 128.6,
      "32": 128.6,
      "33": 128.6,
      "34": 128.6,
      "35": 128.6,
      "36": 128.6,
      "37": 128.6,
      "38": 128.6,
      "39": 128.6,
      "40": 128.6,
      "41": 128.6,
      "42": 128.6,
      "43": 128.6,
      "44": 128.6,
      "45": 128.6,
      "46": 128.6,
      "47": 128.6,
      "48": 128.6,
      "49": 128.6,
      "50": 128.6,
      "51": 128.6,
      "52": 128.6,
      "53": 128.6,
      "54": 128.6,
      "7": 51.4,
      "8": 51.4,
      "9": 51.4,
      "10": 51.4,
      "11": 51.4,
      "12": 51.4,
      "13": 51.4,
      "14": 51.4,
      "15": 51.4,
      "16": 51.4,
      "17": 51.4,
      "18": 51.4,
      "19": 51.4,
      "20": 51.4,
      "21": 51.4,
      "22": 51.4,
      "23": 51.4,
      "24": 51.4,
      "1": 128.6,
      "2": 128.6,
      "3": 128.6,
      "4": 128.6,
      "5": 128.6,
      "6": 128.6
    }
  },
  {
    "id": 33,
    "angles": {
      "25": 124.6,
      "26": 124.6,
      "27": 124.6,
      "28": 124.6,
      "29": 124.6,
      "30": 124.6,
      "31": 124.6,
      "32": 124.6,
      "33": 124.6,
      "34": 124.6,
      "35": 124.6,
      "36": 124.6,
      "37": 124.6,
      "38": 124.6,
      "39": 124.6,
      "40": 124.6,
      "41": 124.6,
      "42": 124.6,
      "43": 124.6,
      "44": 124.6,
      "45": 124.6,
      "46": 124.6,
      "47": 124.6,
      "48": 124.6,
      "49": 124.6,
      "50": 124.6,
      "51": 124.6,
      "52": 124.6,
      "53": 124.6,
      "54": 124.6,
      "7": 55.4,
      "8": 55.4,
      "9": 55.4,
      "10": 55.4,
      "11": 55.4,
      "12": 55.4,
      "13": 55.4,
      "14": 55.4,
      "15": 55.4,
      "16": 55.4,
      "17": 55.4,
      "18": 55.4,
      "19": 55.4,
      "20": 55.4,
      "21": 55.4,
      "22": 55.4,
      "23": 55.4,
      "24": 55.4,
      "1": 124.6,
      "2": 124.6,
      "3": 124.6,
      "4": 124.6,
      "5": 124.6,
      "6": 124.6
    }
  },
  {
    "id": 34,
    "angles": {
      "25": 118.3,
      "26": 118.3,
      "27": 118.3,
      "28": 118.3,
      "29": 118.3,
      "30": 118.3,
      "31": 118.3,
      "32": 118.3,
      "33": 118.3,
      "34": 118.3,
      "35": 118.3,
      "36": 118.3,
      "37": 118.3,
      "38": 118.3,
      "39": 118.3,
      "40": 118.3,
      "41": 118.3,
      "42": 118.3,
      "43": 118.3,
      "44": 118.3,
      "45": 118.3,
      "46": 118.3,
      "47": 118.3,
      "48": 118.3,
      "49": 118.3,
      "50": 118.3,
      "51": 118.3,
      "52": 118.3,
      "53": 118.3,
      "54": 118.3,
      "7": 61.7,
      "8": 61.7,
      "9": 61.7,
      "10": 61.7,
      "11": 61.7,
      "12": 61.7,
      "13": 61.7,
      "14": 61.7,
      "15": 61.7,
      "16": 61.7,
      "17": 61.7,
      "18": 61.7,
      "19": 61.7,
      "20": 61.7,
      "21": 61.7,
      "22": 61.7,
      "23": 61.7,
      "24": 61.7,
      "1": 118.3,
      "2": 118.3,
      "3": 118.3,
      "4": 118.3,
      "5": 118.3,
      "6": 118.3
    }
  },
  {
    "id": 35,
    "angles": {
      "25": 110.0,
      "26": 110.0,
      "27": 110.0,
      "28": 110.0,
      "29": 110.0,
      "30": 110.0,
      "31": 110.0,
      "32": 110.0,
      "33": 110.0,
      "34": 110.0,
      "35": 110.0,
      "36": 110.0,
      "37": 110.0,
      "38": 110.0,
      "39": 110.0,
      "40": 110.0,
      "41": 110.0,
      "42": 110.0,
      "43": 110.0,
      "44": 110.0,
      "45": 110.0,
      "46": 110.0,
      "47": 110.0,
      "48": 110.0,
      "49": 110.0,
      "50": 110.0,
      "51": 110.0,
      "52": 110.0,
      "53": 110.0,
      "54": 110.0,
      "7": 70.0,
      "8": 70.0,
      "9": 70.0,
      "10": 70.0,
      "11": 70.0,
      "12": 70.0,
      "13": 70.0,
      "14": 70.0,
      "15": 70.0,
      "16": 70.0,
      "17": 70.0,
      "18": 70.0,
      "19": 70.0,
      "20": 70.0,
      "21": 70.0,
      "22": 70.0,
      "23": 70.0,
      "24": 70.0,
      "1": 110.0,
      "2": 110.0,
      "3": 110.0,
      "4": 110.0,
      "5": 110.0,
      "6": 110.0
    }
  },
  {
    "id": 36,
    "angles": {
      "25": 100.4,
      "26": 100.4,
      "27": 100.4,
      "28": 100.4,
      "29": 100.4,
      "30": 100.4,
      "31": 100.4,
      "32": 100.4,
      "33": 100.4,
      "34": 100.4,
      "35": 100.4,
      "36": 100.4,
      "37": 100.4,
      "38": 100.4,
      "39": 100.4,
      "40": 100.4,
      "41": 100.4,
      "42": 100.4,
      "43": 100.4,
      "44": 100.4,
      "45": 100.4,
      "46": 100.4,
      "47": 100.4,
      "48": 100.4,
      "49": 100.4,
      "50": 100.4,
      "51": 100.4,
      "52": 100.4,
      "53": 100.4,
      "54": 100.4,
      "7": 79.6,
      "8": 79.6,
      "9": 79.6,
      "10": 79.6,
      "11": 79.6,
      "12": 79.6,
      "13": 79.6,
      "14": 79.6,
      "15": 79.6,
      "16": 79.6,
      "17": 79.6,
      "18": 79.6,
      "19": 79.6,
      "20": 79.6,
      "21": 79.6,
      "22": 79.6,
      "23": 79.6,
      "24": 79.6,
      "1": 100.4,
      "2": 100.4,
      "3": 100.4,
      "4": 100.4,
      "5": 100.4,
      "6": 100.4
    }
  },
  {
    "id": 37,
    "angles": {
      "25": 90.0,
      "26": 90.0,
      "27": 90.0,
      "28": 90.0,
      "29": 90.0,
      "30": 90.0,
      "31": 90.0,
      "32": 90.0,
      "33": 90.0,
      "34": 90.0,
      "35": 90.0,
      "36": 90.0,
      "37": 90.0,
      "38": 90.0,
      "39": 90.0,
      "40": 90.0,
      "41": 90.0,
      "42": 90.0,
      "43": 90.0,
      "44": 90.0,
      "45": 90.0,
      "46": 90.0,
      "47": 90.0,
      "48": 90.0,
      "49": 90.0,
      "50": 90.0,
      "51": 90.0,
      "52": 90.0,
      "53": 90.0,
      "54": 90.0,
      "7": 90.0,
      "8": 90.0,
      "9": 90.0,
      "10": 90.0,
      "11": 90.0,
      "12": 90.0,
      "13": 90.0,
      "14": 90.0,
      "15": 90.0,
      "16": 90.0,
      "17": 90.0,
      "18": 90.0,
      "19": 90.0,
      "20": 90.0,
      "21": 90.0,
      "22": 90.0,
      "23": 90.0,
      "24": 90.0,
      "1": 90.0,
      "2": 90.0,
      "3": 90.0,
      "4": 90.0,
      "5": 90.0,
      "6": 90.0
    }
  },
  {
    "id": 38,
    "angles": {
      "25": 79.6,
      "26": 79.6,
      "27": 79.6,
      "28": 79.6,
      "29": 79.6,
      "30": 79.6,
      "31": 79.6,
      "32": 79.6,
      "33": 79.6,
      "34": 79.6,
      "35": 79.6,
      "36": 79.6,
      "37": 79.6,
      "38": 79.6,
      "39": 79.6,
      "40": 79.6,
      "41": 79.6,
      "42": 79.6,
      "43": 79.6,
      "44": 79.6,
      "45": 79.6,
      "46": 79.6,
      "47": 79.6,
      "48": 79.6,
      "49": 79.6,
      "50": 79.6,
      "51": 79.6,
      "52": 79.6,
      "53": 79.6,
      "54": 79.6,
      "7": 100.4,
      "8": 100.4,
      "9": 100.4,
      "10": 100.4,
      "11": 100.4,
      "12": 100.4,
      "13": 100.4,
      "14": 100.4,
      "15": 100.4,
      "16": 100.4,
      "17": 100.4,
      "18": 100.4,
      "19": 100.4,
      "20": 100.4,
      "21": 100.4,
      "22": 100.4,
      "23": 100.4,
      "24": 100.4,
      "1": 79.6,
      "2": 79.6,
      "3": 79.6,
      "4": 79.6,
      "5": 79.6,
      "6": 79.6
    }
  },
  {
    "id": 39,
    "angles": {
      "25": 70.0,
      "26": 70.0,
      "27": 70.0,
      "28": 70.0,
      "29": 70.0,
      "30": 70.0,
      "31": 70.0,
      "32": 70.0,
      "33": 70.0,
      "34": 70.0,
      "35": 70.0,
      "36": 70.0,
      "37": 70.0,
      "38": 70.0,
      "39": 70.0,
      "40": 70.0,
      "41": 70.0,
      "42": 70.0,
      "43": 70.0,
      "44": 70.0,
      "45": 70.0,
      "46": 70.0,
      "47": 70.0,
      "48": 70.0,
      "49": 70.0,
      "50": 70.0,
      "51": 70.0,
      "52": 70.0,
      "53": 70.0,
      "54": 70.0,
      "7": 110.0,
      "8": 110.0,
      "9": 110.0,
      "10": 110.0,
      "11": 110.0,
      "12": 110.0,
      "13": 110.0,
      "14": 110.0,
      "15": 110.0,
      "16": 110.0,
      "17": 110.0,
      "18": 110.0,
      "19": 110.0,
      "20": 110.0,
      "21": 110.0,
      "22": 110.0,
      "23": 110.0,
      "24": 110.0,
      "1": 70.0,
      "2": 70.0,
      "3": 70.0,
      "4": 70.0,
      "5": 70.0,
      "6": 70.0
    }
  },
  {
    "id": 40,
    "angles": {
      "25": 61.7,
      "26": 61.7,
      "27": 61.7,
      "28": 61.7,
      "29": 61.7,
      "30": 61.7,
      "31": 61.7,
      "32": 61.7,
      "33": 61.7,
      "34": 61.7,
      "35": 61.7,
      "36": 61.7,
      "37": 61.7,
      "38": 61.7,
      "39": 61.7,
      "40": 61.7,
      "41": 61.7,
      "42": 61.7,
      "43": 61.7,
      "44": 61.7,
      "45": 61.7,
      "46": 61.7,
      "47": 61.7,
      "48": 61.7,
      "49": 61.7,
      "50": 61.7,
      "51": 61.7,
      "52": 61.7,
      "53": 61.7,
      "54": 61.7,
      "7": 118.3,
      "8": 118.3,
      "9": 118.3,
      "10": 118.3,
      "11": 118.3,
      "12": 118.3,
      "13": 118.3,
      "14": 118.3,
      "15": 118.3,
      "16": 118.3,
      "17": 118.3,
      "18": 118.3,
      "19": 118.3,
      "20": 118.3,
      "21": 118.3,
      "22": 118.3,
      "23": 118.3,
      "24": 118.3,
      "1": 61.7,
      "2": 61.7,
      "3": 61.7,
      "4": 61.7,
      "5": 61.7,
      "6": 61.7
    }
  },
  {
    "id": 41,
    "angles": {
      "25": 55.4,
      "26": 55.4,
      "27": 55.4,
      "28": 55.4,
      "29": 55.4,
      "30": 55.4,
      "31": 55.4,
      "32": 55.4,
      "33": 55.4,
      "34": 55.4,
      "35": 55.4,
      "36": 55.4,
      "37": 55.4,
      "38": 55.4,
      "39": 55.4,
      "40": 55.4,
      "41": 55.4,
      "42": 55.4,
      "43": 55.4,
      "44": 55.4,
      "45": 55.4,
      "46": 55.4,
      "47": 55.4,
      "48": 55.4,
      "49": 55.4,
      "50": 55.4,
      "51": 55.4,
      "52": 55.4,
      "53": 55.4,
      "54": 55.4,
      "7": 124.6,
      "8": 124.6,
      "9": 124.6,
      "10": 124.6,
      "11": 124.6,
      "12": 124.6,
      "13": 124.6,
      "14": 124.6,
      "15": 124.6,
      "16": 124.6,
      "17": 124.6,
      "18": 124.6,
      "19": 124.6,
      "20": 124.6,
      "21": 124.6,
      "22": 124.6,
      "23": 124.6,
      "24": 124.6,
      "1": 55.4,
      "2": 55.4,
      "3": 55.4,
      "4": 55.4,
      "5": 55.4,
      "6": 55.4
    }
  },
  {
    "id": 42,
    "angles": {
      "25": 51.4,
      "26": 51.4,
      "27": 51.4,
      "28": 51.4,
      "29": 51.4,
      "30": 51.4,
      "31": 51.4,
      "32": 51.4,
      "33": 51.4,
      "34": 51.4,
      "35": 51.4,
      "36": 51.4,
      "37": 51.4,
      "38": 51.4,
      "39": 51.4,
      "40": 51.4,
      "41": 51.4,
      "42": 51.4,
      "43": 51.4,
      "44": 51.4,
      "45": 51.4,
      "46": 51.4,
      "47": 51.4,
      "48": 51.4,
      "49": 51.4,
      "50": 51.4,
      "51": 51.4,
      "52": 51.4,
      "53": 51.4,
      "54": 51.4,
      "7": 128.6,
      "8": 128.6,
      "9": 128.6,
      "10": 128.6,
      "11": 128.6,
      "12": 128.6,
      "13": 128.6,
      "14": 128.6,
      "15": 128.6,
      "16": 128.6,
      "17": 128.6,
      "18": 128.6,
      "19": 128.6,
      "20": 128.6,
      "21": 128.6,
      "22": 128.6,
      "23": 128.6,
      "24": 128.6,
      "1": 51.4,
      "2": 51.4,
      "3": 51.4,
      "4": 51.4,
      "5": 51.4,
      "6": 51.4
    }
  },
  {
    "id": 43,
    "angles": {
      "25": 50.0,
      "26": 50.0,
      "27": 50.0,
      "28": 50.0,
      "29": 50.0,
      "30": 50.0,
      "31": 50.0,
      "32": 50.0,
      "33": 50.0,
      "34": 50.0,
      "35": 50.0,
      "36": 50.0,
      "37": 50.0,
      "38": 50.0,
      "39": 50.0,
      "40": 50.0,
      "41": 50.0,
      "42": 50.0,
      "43": 50.0,
      "44": 50.0,
      "45": 50.0,
      "46": 50.0,
      "47": 50.0,
      "48": 50.0,
      "49": 50.0,
      "50": 50.0,
      "51": 50.0,
      "52": 50.0,
      "53": 50.0,
      "54": 50.0,
      "7": 130.0,
      "8": 130.0,
      "9": 130.0,
      "10": 130.0,
      "11": 130.0,
      "12": 130.0,
      "13": 130.0,
      "14": 130.0,
      "15": 130.0,
      "16": 130.0,
      "17": 130.0,
      "18": 130.0,
      "19": 130.0,
      "20": 130.0,
      "21": 130.0,
      "22": 130.0,
      "23": 130.0,
      "24": 130.0,
      "1": 50.0,
      "2": 50.0,
      "3": 50.0,
      "4": 50.0,
      "5": 50.0,
      "6": 50.0
    }
  },
  {
    "id": 44,
    "angles": {
      "25": 51.4,
      "26": 51.4,
      "27": 51.4,
      "28": 51.4,
      "29": 51.4,
      "30": 51.4,
      "31": 51.4,
      "32": 51.4,
      "33": 51.4,
      "34": 51.4,
      "35": 51.4,
      "36": 51.4,
      "37": 51.4,
      "38": 51.4,
      "39": 51.4,
      "40": 51.4,
      "41": 51.4,
      "42": 51.4,
      "43": 51.4,
      "44": 51.4,
      "45": 51.4,
      "46": 51.4,
      "47": 51.4,
      "48": 51.4,
      "49": 51.4,
      "50": 51.4,
      "51": 51.4,
      "52": 51.4,
      "53": 51.4,
      "54": 51.4,
      "7": 128.6,
      "8": 128.6,
      "9": 128.6,
      "10": 128.6,
      "11": 128.6,
      "12": 128.6,
      "13": 128.6,
      "14": 128.6,
      "15": 128.6,
      "16": 128.6,
      "17": 128.6,
      "18": 128.6,
      "19": 128.6,
      "20": 128.6,
      "21": 128.6,
      "22": 128.6,
      "23": 128.6,
      "24": 128.6,
      "1": 51.4,
      "2": 51.4,
      "3": 51.4,
      "4": 51.4,
      "5": 51.4,
      "6": 51.4
    }
  },
  {
    "id": 45,
    "angles": {
      "25": 55.4,
      "26": 55.4,
      "27": 55.4,
      "28": 55.4,
      "29": 55.4,
      "30": 55.4,
      "31": 55.4,
      "32": 55.4,
      "33": 55.4,
      "34": 55.4,
      "35": 55.4,
      "36": 55.4,
      "37": 55.4,
      "38": 55.4,
      "39": 55.4,
      "40": 55.4,
      "41": 55.4,
      "42": 55.4,
      "43": 55.4,
      "44": 55.4,
      "45": 55.4,
      "46": 55.4,
      "47": 55.4,
      "48": 55.4,
      "49": 55.4,
      "50": 55.4,
      "51": 55.4,
      "52": 55.4,
      "53": 55.4,
      "54": 55.4,
      "7": 124.6,
      "8": 124.6,
      "9": 124.6,
      "10": 124.6,
      "11": 124.6,
      "12": 124.6,
      "13": 124.6,
      "14": 124.6,
      "15": 124.6,
      "16": 124.6,
      "17": 124.6,
      "18": 124.6,
      "19": 124.6,
      "20": 124.6,
      "21": 124.6,
      "22": 124.6,
      "23": 124.6,
      "24": 124.6,
      "1": 55.4,
      "2": 55.4,
      "3": 55.4,
      "4": 55.4,
      "5": 55.4,
      "6": 55.4
    }
  },
  {
    "id": 46,
    "angles": {
      "25": 61.7,
      "26": 61.7,
      "27": 61.7,
      "28": 61.7,
      "29": 61.7,
      "30": 61.7,
      "31": 61.7,
      "32": 61.7,
      "33": 61.7,
      "34": 61.7,
      "35": 61.7,
      "36": 61.7,
      "37": 61.7,
      "38": 61.7,
      "39": 61.7,
      "40": 61.7,
      "41": 61.7,
      "42": 61.7,
      "43": 61.7,
      "44": 61.7,
      "45": 61.7,
      "46": 61.7,
      "47": 61.7,
      "48": 61.7,
      "49": 61.7,
      "50": 61.7,
      "51": 61.7,
      "52": 61.7,
      "53": 61.7,
      "54": 61.7,
      "7": 118.3,
      "8": 118.3,
      "9": 118.3,
      "10": 118.3,
      "11": 118.3,
      "12": 118.3,
      "13": 118.3,
      "14": 118.3,
      "15": 118.3,
      "16": 118.3,
      "17": 118.3,
      "18": 118.3,
      "19": 118.3,
      "20": 118.3,
      "21": 118.3,
      "22": 118.3,
      "23": 118.3,
      "24": 118.3,
      "1": 61.7,
      "2": 61.7,
      "3": 61.7,
      "4": 61.7,
      "5": 61.7,
      "6": 61.7
    }
  },
  {
    "id": 47,
    "angles": {
      "25": 70.0,
      "26": 70.0,
      "27": 70.0,
      "28": 70.0,
      "29": 70.0,
      "30": 70.0,
      "31": 70.0,
      "32": 70.0,
      "33": 70.0,
      "34": 70.0,
      "35": 70.0,
      "36": 70.0,
      "37": 70.0,
      "38": 70.0,
      "39": 70.0,
      "40": 70.0,
      "41": 70.0,
      "42": 70.0,
      "43": 70.0,
      "44": 70.0,
      "45": 70.0,
      "46": 70.0,
      "47": 70.0,
      "48": 70.0,
      "49": 70.0,
      "50": 70.0,
      "51": 70.0,
      "52": 70.0,
      "53": 70.0,
      "54": 70.0,
      "7": 110.0,
      "8": 110.0,
      "9": 110.0,
      "10": 110.0,
      "11": 110.0,
      "12": 110.0,
      "13": 110.0,
      "14": 110.0,
      "15": 110.0,
      "16": 110.0,
      "17": 110.0,
      "18": 110.0,
      "19": 110.0,
      "20": 110.0,
      "21": 110.0,
      "22": 110.0,
      "23": 110.0,
      "24": 110.0,
      "1": 70.0,
      "2": 70.0,
      "3": 70.0,
      "4": 70.0,
      "5": 70.0,
      "6": 70.0
    }
  },
  {
    "id": 48,
    "angles": {
      "25": 79.6,
      "26": 79.6,
      "27": 79.6,
      "28": 79.6,
      "29": 79.6,
      "30": 79.6,
      "31": 79.6,
      "32": 79.6,
      "33": 79.6,
      "34": 79.6,
      "35": 79.6,
      "36": 79.6,
      "37": 79.6,
      "38": 79.6,
      "39": 79.6,
      "40": 79.6,
      "41": 79.6,
      "42": 79.6,
      "43": 79.6,
      "44": 79.6,
      "45": 79.6,
      "46": 79.6,
      "47": 79.6,
      "48": 79.6,
      "49": 79.6,
      "50": 79.6,
      "51": 79.6,
      "52": 79.6,
      "53": 79.6,
      "54": 79.6,
      "7": 100.4,
      "8": 100.4,
      "9": 100.4,
      "10": 100.4,
      "11": 100.4,
      "12": 100.4,
      "13": 100.4,
      "14": 100.4,
      "15": 100.4,
      "16": 100.4,
      "17": 100.4,
      "18": 100.4,
      "19": 100.4,
      "20": 100.4,
      "21": 100.4,
      "22": 100.4,
      "23": 100.4,
      "24": 100.4,
      "1": 79.6,
      "2": 79.6,
      "3": 79.6,
      "4": 79.6,
      "5": 79.6,
      "6": 79.6
    }
  },
  {
    "id": 49,
    "angles": {
      "25": 90.0,
      "26": 90.0,
      "27": 90.0,
      "28": 90.0,
      "29": 90.0,
      "30": 90.0,
      "31": 90.0,
      "32": 90.0,
      "33": 90.0,
      "34": 90.0,
      "35": 90.0,
      "36": 90.0,
      "37": 90.0,
      "38": 90.0,
      "39": 90.0,
      "40": 90.0,
      "41": 90.0,
      "42": 90.0,
      "43": 90.0,
      "44": 90.0,
      "45": 90.0,
      "46": 90.0,
      "47": 90.0,
      "48": 90.0,
      "49": 90.0,
      "50": 90.0,
      "51": 90.0,
      "52": 90.0,
      "53": 90.0,
      "54": 90.0,
      "7": 90.0,
      "8": 90.0,
      "9": 90.0,
      "10": 90.0,
      "11": 90.0,
      "12": 90.0,
      "13": 90.0,
      "14": 90.0,
      "15": 90.0,
      "16": 90.0,
      "17": 90.0,
      "18": 90.0,
      "19": 90.0,
      "20": 90.0,
      "21": 90.0,
      "22": 90.0,
      "23": 90.0,
      "24": 90.0,
      "1": 90.0,
      "2": 90.0,
      "3": 90.0,
      "4": 90.0,
      "5": 90.0,
      "6": 90.0
    }
  },
  {
    "id": 50,
    "angles": {
      "25": 100.4,
      "26": 100.4,
      "27": 100.4,
      "28": 100.4,
      "29": 100.4,
      "30": 100.4,
      "31": 100.4,
      "32": 100.4,
      "33": 100.4,
      "34": 100.4,
      "35": 100.4,
      "36": 100.4,
      "37": 100.4,
      "38": 100.4,
      "39": 100.4,
      "40": 100.4,
      "41": 100.4,
      "42": 100.4,
      "43": 100.4,
      "44": 100.4,
      "45": 100.4,
      "46": 100.4,
      "47": 100.4,
      "48": 100.4,
      "49": 100.4,
      "50": 100.4,
      "51": 100.4,
      "52": 100.4,
      "53": 100.4,
      "54": 100.4,
      "7": 79.6,
      "8": 79.6,
      "9": 79.6,
      "10": 79.6,
      "11": 79.6,
      "12": 79.6,
      "13": 79.6,
      "14": 79.6,
      "15": 79.6,
      "16": 79.6,
      "17": 79.6,
      "18": 79.6,
      "19": 79.6,
      "20": 79.6,
      "21": 79.6,
      "22": 79.6,
      "23": 79.6,
      "24": 79.6,
      "1": 100.4,
      "2": 100.4,
      "3": 100.4,
      "4": 100.4,
      "5": 100.4,
      "6": 100.4
    }
  },
  {
    "id": 51,
    "angles": {
      "25": 110.0,
      "26": 110.0,
      "27": 110.0,
      "28": 110.0,
      "29": 110.0,
      "30": 110.0,
      "31": 110.0,
      "32": 110.0,
      "33": 110.0,
      "34": 110.0,
      "35": 110.0,
      "36": 110.0,
      "37": 110.0,
      "38": 110.0,
      "39": 110.0,
      "40": 110.0,
      "41": 110.0,
      "42": 110.0,
      "43": 110.0,
      "44": 110.0,
      "45": 110.0,
      "46": 110.0,
      "47": 110.0,
      "48": 110.0,
      "49": 110.0,
      "50": 110.0,
      "51": 110.0,
      "52": 110.0,
      "53": 110.0,
      "54": 110.0,
      "7": 70.0,
      "8": 70.0,
      "9": 70.0,
      "10": 70.0,
      "11": 70.0,
      "12": 70.0,
      "13": 70.0,
      "14": 70.0,
      "15": 70.0,
      "16": 70.0,
      "17": 70.0,
      "18": 70.0,
      "19": 70.0,
      "20": 70.0,
      "21": 70.0,
      "22": 70.0,
      "23": 70.0,
      "24": 70.0,
      "1": 110.0,
      "2": 110.0,
      "3": 110.0,
      "4": 110.0,
      "5": 110.0,
      "6": 110.0
    }
  },
  {
    "id": 52,
    "angles": {
      "25": 118.3,
      "26": 118.3,
      "27": 118.3,
      "28": 118.3,
      "29": 118.3,
      "30": 118.3,
      "31": 118.3,
      "32": 118.3,
      "33": 118.3,
      "34": 118.3,
      "35": 118.3,
      "36": 118.3,
      "37": 118.3,
      "38": 118.3,
      "39": 118.3,
      "40": 118.3,
      "41": 118.3,
      "42": 118.3,
      "43": 118.3,
      "44": 118.3,
      "45": 118.3,
      "46": 118.3,
      "47": 118.3,
      "48": 118.3,
      "49": 118.3,
      "50": 118.3,
      "51": 118.3,
      "52": 118.3,
      "53": 118.3,
      "54": 118.3,
      "7": 61.7,
      "8": 61.7,
      "9": 61.7,
      "10": 61.7,
      "11": 61.7,
      "12": 61.7,
      "13": 61.7,
      "14": 61.7,
      "15": 61.7,
      "16": 61.7,
      "17": 61.7,
      "18": 61.7,
      "19": 61.7,
      "20": 61.7,
      "21": 61.7,
      "22": 61.7,
      "23": 61.7,
      "24": 61.7,
      "1": 118.3,
      "2": 118.3,
      "3": 118.3,
      "4": 118.3,
      "5": 118.3,
      "6": 118.3
    }
  },
  {
    "id": 53,
    "angles": {
      "25": 124.6,
      "26": 124.6,
      "27": 124.6,
      "28": 124.6,
      "29": 124.6,
      "30": 124.6,
      "31": 124.6,
      "32": 124.6,
      "33": 124.6,
      "34": 124.6,
      "35": 124.6,
      "36": 124.6,
      "37": 124.6,
      "38": 124.6,
      "39": 124.6,
      "40": 124.6,
      "41": 124.6,
      "42": 124.6,
      "43": 124.6,
      "44": 124.6,
      "45": 124.6,
      "46": 124.6,
      "47": 124.6,
      "48": 124.6,
      "49": 124.6,
      "50": 124.6,
      "51": 124.6,
      "52": 124.6,
      "53": 124.6,
      "54": 124.6,
      "7": 55.4,
      "8": 55.4,
      "9": 55.4,
      "10": 55.4,
      "11": 55.4,
      "12": 55.4,
      "13": 55.4,
      "14": 55.4,
      "15": 55.4,
      "16": 55.4,
      "17": 55.4,
      "18": 55.4,
      "19": 55.4,
      "20": 55.4,
      "21": 55.4,
      "22": 55.4,
      "23": 55.4,
      "24": 55.4,
      "1": 124.6,
      "2": 124.6,
      "3": 124.6,
      "4": 124.6,
      "5": 124.6,
      "6": 124.6
    }
  },
  {
    "id": 54,
    "angles": {
      "25": 128.6,
      "26": 128.6,
      "27": 128.6,
      "28": 128.6,
      "29": 128.6,
      "30": 128.6,
      "31": 128.6,
      "32": 128.6,
      "33": 128.6,
      "34": 128.6,
      "35": 128.6,
      "36": 128.6,
      "37": 128.6,
      "38": 128.6,
      "39": 128.6,
      "40": 128.6,
      "41": 128.6,
      "42": 128.6,
      "43": 128.6,
      "44": 128.6,
      "45": 128.6,
      "46": 128.6,
      "47": 128.6,
      "48": 128.6,
      "49": 128.6,
      "50": 128.6,
      "51": 128.6,
      "52": 128.6,
      "53": 128.6,
      "54": 128.6,
      "7": 51.4,
      "8": 51.4,
      "9": 51.4,
      "10": 51.4,
      "11": 51.4,
      "12": 51.4,
      "13": 51.4,
      "14": 51.4,
      "15": 51.4,
      "16": 51.4,
      "17": 51.4,
      "18": 51.4,
      "19": 51.4,
      "20": 51.4,
      "21": 51.4,
      "22": 51.4,
      "23": 51.4,
      "24": 51.4,
      "1": 128.6,
      "2": 128.6,
      "3": 128.6,
      "4": 128.6,
      "5": 128.6,
      "6": 128.6
    }
  },
  {
    "id": 55,
    "angles": {
      "25": 130.0,
      "26": 130.0,
      "27": 130.0,
      "28": 130.0,
      "29": 130.0,
      "30": 130.0,
      "31": 130.0,
      "32": 130.0,
      "33": 130.0,
      "34": 130.0,
      "35": 130.0,
      "36": 130.0,
      "37": 130.0,
      "38": 130.0,
      "39": 130.0,
      "40": 130.0,
      "41": 130.0,
      "42": 130.0,
      "43": 130.0,
      "44": 130.0,
      "45": 130.0,
      "46": 130.0,
      "47": 130.0,
      "48": 130.0,
      "49": 130.0,
      "50": 130.0,
      "51": 130.0,
      "52": 130.0,
      "53": 130.0,
      "54": 130.0,
      "7": 50.0,
      "8": 50.0,
      "9": 50.0,
      "10": 50.0,
      "11": 50.0,
      "12": 50.0,
      "13": 50.0,
      "14": 50.0,
      "15": 50.0,
      "16": 50.0,
      "17": 50.0,
      "18": 50.0,
      "19": 50.0,
      "20": 50.0,
      "21": 50.0,
      "22": 50.0,
      "23": 50.0,
      "24": 50.0,
      "1": 130.0,
      "2": 130.0,
      "3": 130.0,
      "4": 130.0,
      "5": 130.0,
      "6": 130.0
    }
  },
  {
    "id": 56,
    "angles": {
      "25": 128.6,
      "26": 128.6,
      "27": 128.6,
      "28": 128.6,
      "29": 128.6,
      "30": 128.6,
      "31": 128.6,
      "32": 128.6,
      "33": 128.6,
      "34": 128.6,
      "35": 128.6,
      "36": 128.6,
      "37": 128.6,
      "38": 128.6,
      "39": 128.6,
      "40": 128.6,
      "41": 128.6,
      "42": 128.6,
      "43": 128.6,
      "44": 128.6,
      "45": 128.6,
      "46": 128.6,
      "47": 128.6,
      "48": 128.6,
      "49": 128.6,
      "50": 128.6,
      "51": 128.6,
      "52": 128.6,
      "53": 128.6,
      "54": 128.6,
      "7": 51.4,
      "8": 51.4,
      "9": 51.4,
      "10": 51.4,
      "11": 51.4,
      "12": 51.4,
      "13": 51.4,
      "14": 51.4,
      "15": 51.4,
      "16": 51.4,
      "17": 51.4,
      "18": 51.4,
      "19": 51.4,
      "20": 51.4,
      "21": 51.4,
      "22": 51.4,
      "23": 51.4,
      "24": 51.4,
      "1": 128.6,
      "2": 128.6,
      "3": 128.6,
      "4": 128.6,
      "5": 128.6,
      "6": 128.6
    }
  },
  {
    "id": 57,
    "angles": {
      "25": 124.6,
      "26": 124.6,
      "27": 124.6,
      "28": 124.6,
      "29": 124.6,
      "30": 124.6,
      "31": 124.6,
      "32": 124.6,
      "33": 124.6,
      "34": 124.6,
      "35": 124.6,
      "36": 124.6,
      "37": 124.6,
      "38": 124.6,
      "39": 124.6,
      "40": 124.6,
      "41": 124.6,
      "42": 124.6,
      "43": 124.6,
      "44": 124.6,
      "45": 124.6,
      "46": 124.6,
      "47": 124.6,
      "48": 124.6,
      "49": 124.6,
      "50": 124.6,
      "51": 124.6,
      "52": 124.6,
      "53": 124.6,
      "54": 124.6,
      "7": 55.4,
      "8": 55.4,
      "9": 55.4,
      "10": 55.4,
      "11": 55.4,
      "12": 55.4,
      "13": 55.4,
      "14": 55.4,
      "15": 55.4,
      "16": 55.4,
      "17": 55.4,
      "18": 55.4,
      "19": 55.4,
      "20": 55.4,
      "21": 55.4,
      "22": 55.4,
      "23": 55.4,
      "24": 55.4,
      "1": 124.6,
      "2": 124.6,
      "3": 124.6,
      "4": 124.6,
      "5": 124.6,
      "6": 124.6
    }
  },
  {
    "id": 58,
    "angles": {
      "25": 118.3,
      "26": 118.3,
      "27": 118.3,
      "28": 118.3,
      "29": 118.3,
      "30": 118.3,
      "31": 118.3,
      "32": 118.3,
      "33": 118.3,
      "34": 118.3,
      "35": 118.3,
      "36": 118.3,
      "37": 118.3,
      "38": 118.3,
      "39": 118.3,
      "40": 118.3,
      "41": 118.3,
      "42": 118.3,
      "43": 118.3,
      "44": 118.3,
      "45": 118.3,
      "46": 118.3,
      "47": 118.3,
      "48": 118.3,
      "49": 118.3,
      "50": 118.3,
      "51": 118.3,
      "52": 118.3,
      "53": 118.3,
      "54": 118.3,
      "7": 61.7,
      "8": 61.7,
      "9": 61.7,
      "10": 61.7,
      "11": 61.7,
      "12": 61.7,
      "13": 61.7,
      "14": 61.7,
      "15": 61.7,
      "16": 61.7,
      "17": 61.7,
      "18": 61.7,
      "19": 61.7,
      "20": 61.7,
      "21": 61.7,
      "22": 61.7,
      "23": 61.7,
      "24": 61.7,
      "1": 118.3,
      "2": 118.3,
      "3": 118.3,
      "4": 118.3,
      "5": 118.3,
      "6": 118.3
    }
  },
  {
    "id": 59,
    "angles": {
      "25": 110.0,
      "26": 110.0,
      "27": 110.0,
      "28": 110.0,
      "29": 110.0,
      "30": 110.0,
      "31": 110.0,
      "32": 110.0,
      "33": 110.0,
      "34": 110.0,
      "35": 110.0,
      "36": 110.0,
      "37": 110.0,
      "38": 110.0,
      "39": 110.0,
      "40": 110.0,
      "41": 110.0,
      "42": 110.0,
      "43": 110.0,
      "44": 110.0,
      "45": 110.0,
      "46": 110.0,
      "47": 110.0,
      "48": 110.0,
      "49": 110.0,
      "50": 110.0,
      "51": 110.0,
      "52": 110.0,
      "53": 110.0,
      "54": 110.0,
      "7": 70.0,
      "8": 70.0,
      "9": 70.0,
      "10": 70.0,
      "11": 70.0,
      "12": 70.0,
      "13": 70.0,
      "14": 70.0,
      "15": 70.0,
      "16": 70.0,
      "17": 70.0,
      "18": 70.0,
      "19": 70.0,
      "20": 70.0,
      "21": 70.0,
      "22": 70.0,
      "23": 70.0,
      "24": 70.0,
      "1": 110.0,
      "2": 110.0,
      "3": 110.0,
      "4": 110.0,
      "5": 110.0,
      "6": 110.0
    }
  },
  {
    "id": 60,
    "angles": {
      "25": 100.4,
      "26": 100.4,
      "27": 100.4,
      "28": 100.4,
      "29": 100.4,
      "30": 100.4,
      "31": 100.4,
      "32": 100.4,
      "33": 100.4,
      "34": 100.4,
      "35": 100.4,
      "36": 100.4,
      "37": 100.4,
      "38": 100.4,
      "39": 100.4,
      "40": 100.4,
      "41": 100.4,
      "42": 100.4,
      "43": 100.4,
      "44": 100.4,
      "45": 100.4,
      "46": 100.4,
      "47": 100.4,
      "48": 100.4,
      "49": 100.4,
      "50": 100.4,
      "51": 100.4,
      "52": 100.4,
      "53": 100.4,
      "54": 100.4,
      "7": 79.6,
      "8": 79.6,
      "9": 79.6,
      "10": 79.6,
      "11": 79.6,
      "12": 79.6,
      "13": 79.6,
      "14": 79.6,
      "15": 79.6,
      "16": 79.6,
      "17": 79.6,
      "18": 79.6,
      "19": 79.6,
      "20": 79.6,
      "21": 79.6,
      "22": 79.6,
      "23": 79.6,
      "24": 79.6,
      "1": 100.4,
      "2": 100.4,
      "3": 100.4,
      "4": 100.4,
      "5": 100.4,
      "6": 100.4
    }
  },
  {
    "id": 61,
    "angles": {
      "25": 90.0,
      "26": 90.0,
      "27": 90.0,
      "28": 90.0,
      "29": 90.0,
      "30": 90.0,
      "31": 90.0,
      "32": 90.0,
      "33": 90.0,
      "34": 90.0,
      "35": 90.0,
      "36": 90.0,
      "37": 90.0,
      "38": 90.0,
      "39": 90.0,
      "40": 90.0,
      "41": 90.0,
      "42": 90.0,
      "43": 90.0,
      "44": 90.0,
      "45": 90.0,
      "46": 90.0,
      "47": 90.0,
      "48": 90.0,
      "49": 90.0,
      "50": 90.0,
      "51": 90.0,
      "52": 90.0,
      "53": 90.0,
      "54": 90.0,
      "7": 90.0,
      "8": 90.0,
      "9": 90.0,
      "10": 90.0,
      "11": 90.0,
      "12": 90.0,
      "13": 90.0,
      "14": 90.0,
      "15": 90.0,
      "16": 90.0,
      "17": 90.0,
      "18": 90.0,
      "19": 90.0,
      "20": 90.0,
      "21": 90.0,
      "22": 90.0,
      "23": 90.0,
      "24": 90.0,
      "1": 90.0,
      "2": 90.0,
      "3": 90.0,
      "4": 90.0,
      "5": 90.0,
      "6": 90.0
    }
  },
  {
    "id": 62,
    "angles": {
      "25": 79.6,
      "26": 79.6,
      "27": 79.6,
      "28": 79.6,
      "29": 79.6,
      "30": 79.6,
      "31": 79.6,
      "32": 79.6,
      "33": 79.6,
      "34": 79.6,
      "35": 79.6,
      "36": 79.6,
      "37": 79.6,
      "38": 79.6,
      "39": 79.6,
      "40": 79.6,
      "41": 79.6,
      "42": 79.6,
      "43": 79.6,
      "44": 79.6,
      "45": 79.6,
      "46": 79.6,
      "47": 79.6,
      "48": 79.6,
      "49": 79.6,
      "50": 79.6,
      "51": 79.6,
      "52": 79.6,
      "53": 79.6,
      "54": 79.6,
      "7": 100.4,
      "8": 100.4,
      "9": 100.4,
      "10": 100.4,
      "11": 100.4,
      "12": 100.4,
      "13": 100.4,
      "14": 100.4,
      "15": 100.4,
      "16": 100.4,
      "17": 100.4,
      "18": 100.4,
      "19": 100.4,
      "20": 100.4,
      "21": 100.4,
      "22": 100.4,
      "23": 100.4,
      "24": 100.4,
      "1": 79.6,
      "2": 79.6,
      "3": 79.6,
      "4": 79.6,
      "5": 79.6,
      "6": 79.6
    }
  },
  {
    "id": 63,
    "angles": {
      "25": 70.0,
      "26": 70.0,
      "27": 70.0,
      "28": 70.0,
      "29": 70.0,
      "30": 70.0,
      "31": 70.0,
      "32": 70.0,
      "33": 70.0,
      "34": 70.0,
      "35": 70.0,
      "36": 70.0,
      "37": 70.0,
      "38": 70.0,
      "39": 70.0,
      "40": 70.0,
      "41": 70.0,
      "42": 70.0,
      "43": 70.0,
      "44": 70.0,
      "45": 70.0,
      "46": 70.0,
      "47": 70.0,
      "48": 70.0,
      "49": 70.0,
      "50": 70.0,
      "51": 70.0,
      "52": 70.0,
      "53": 70.0,
      "54": 70.0,
      "7": 110.0,
      "8": 110.0,
      "9": 110.0,
      "10": 110.0,
      "11": 110.0,
      "12": 110.0,
      "13": 110.0,
      "14": 110.0,
      "15": 110.0,
      "16": 110.0,
      "17": 110.0,
      "18": 110.0,
      "19": 110.0,
      "20": 110.0,
      "21": 110.0,
      "22": 110.0,
      "23": 110.0,
      "24": 110.0,
      "1": 70.0,
      "2": 70.0,
      "3": 70.0,
      "4": 70.0,
      "5": 70.0,
      "6": 70.0
    }
  },
  {
    "id": 64,
    "angles": {
      "25": 61.7,
      "26": 61.7,
      "27": 61.7,
      "28": 61.7,
      "29": 61.7,
      "30": 61.7,
      "31": 61.7,
      "32": 61.7,
      "33": 61.7,
      "34": 61.7,
      "35": 61.7,
      "36": 61.7,
      "37": 61.7,
      "38": 61.7,
      "39": 61.7,
      "40": 61.7,
      "41": 61.7,
      "42": 61.7,
      "43": 61.7,
      "44": 61.7,
      "45": 61.7,
      "46": 61.7,
      "47": 61.7,
      "48": 61.7,
      "49": 61.7,
      "50": 61.7,
      "51": 61.7,
      "52": 61.7,
      "53": 61.7,
      "54": 61.7,
      "7": 118.3,
      "8": 118.3,
      "9": 118.3,
      "10": 118.3,
      "11": 118.3,
      "12": 118.3,
      "13": 118.3,
      "14": 118.3,
      "15": 118.3,
      "16": 118.3,
      "17": 118.3,
      "18": 118.3,
      "19": 118.3,
      "20": 118.3,
      "21": 118.3,
      "22": 118.3,
      "23": 118.3,
      "24": 118.3,
      "1": 61.7,
      "2": 61.7,
      "3": 61.7,
      "4": 61.7,
      "5": 61.7,
      "6": 61.7
    }
  },
  {
    "id": 65,
    "angles": {
      "25": 55.4,
      "26": 55.4,
      "27": 55.4,
      "28": 55.4,
      "29": 55.4,
      "30": 55.4,
      "31": 55.4,
      "32": 55.4,
      "33": 55.4,
      "34": 55.4,
      "35": 55.4,
      "36": 55.4,
      "37": 55.4,
      "38": 55.4,
      "39": 55.4,
      "40": 55.4,
      "41": 55.4,
      "42": 55.4,
      "43": 55.4,
      "44": 55.4,
      "45": 55.4,
      "46": 55.4,
      "47": 55.4,
      "48": 55.4,
      "49": 55.4,
      "50": 55.4,
      "51": 55.4,
      "52": 55.4,
      "53": 55.4,
      "54": 55.4,
      "7": 124.6,
      "8": 124.6,
      "9": 124.6,
      "10": 124.6,
      "11": 124.6,
      "12": 124.6,
      "13": 124.6,
      "14": 124.6,
      "15": 124.6,
      "16": 124.6,
      "17": 124.6,
      "18": 124.6,
      "19": 124.6,
      "20": 124.6,
      "21": 124.6,
      "22": 124.6,
      "23": 124.6,
      "24": 124.6,
      "1": 55.4,
      "2": 55.4,
      "3": 55.4,
      "4": 55.4,
      "5": 55.4,
      "6": 55.4
    }
  },
  {
    "id": 66,
    "angles": {
      "25": 51.4,
      "26": 51.4,
      "27": 51.4,
      "28": 51.4,
      "29": 51.4,
      "30": 51.4,
      "31": 51.4,
      "32": 51.4,
      "33": 51.4,
      "34": 51.4,
      "35": 51.4,
      "36": 51.4,
      "37": 51.4,
      "38": 51.4,
      "39": 51.4,
      "40": 51.4,
      "41": 51.4,
      "42": 51.4,
      "43": 51.4,
      "44": 51.4,
      "45": 51.4,
      "46": 51.4,
      "47": 51.4,
      "48": 51.4,
      "49": 51.4,
      "50": 51.4,
      "51": 51.4,
      "52": 51.4,
      "53": 51.4,
      "54": 51.4,
      "7": 128.6,
      "8": 128.6,
      "9": 128.6,
      "10": 128.6,
      "11": 128.6,
      "12": 128.6,
      "13": 128.6,
      "14": 128.6,
      "15": 128.6,
      "16": 128.6,
      "17": 128.6,
      "18": 128.6,
      "19": 128.6,
      "20": 128.6,
      "21": 128.6,
      "22": 128.6,
      "23": 128.6,
      "24": 128.6,
      "1": 51.4,
      "2": 51.4,
      "3": 51.4,
      "4": 51.4,
      "5": 51.4,
      "6": 51.4
    }
  },
  {
    "id": 67,
    "angles": {
      "25": 50.0,
      "26": 50.0,
      "27": 50.0,
      "28": 50.0,
      "29": 50.0,
      "30": 50.0,
      "31": 50.0,
      "32": 50.0,
      "33": 50.0,
      "34": 50.0,
      "35": 50.0,
      "36": 50.0,
      "37": 50.0,
      "38": 50.0,
      "39": 50.0,
      "40": 50.0,
      "41": 50.0,
      "42": 50.0,
      "43": 50.0,
      "44": 50.0,
      "45": 50.0,
      "46": 50.0,
      "47": 50.0,
      "48": 50.0,
      "49": 50.0,
      "50": 50.0,
      "51": 50.0,
      "52": 50.0,
      "53": 50.0,
      "54": 50.0,
      "7": 130.0,
      "8": 130.0,
      "9": 130.0,
      "10": 130.0,
      "11": 130.0,
      "12": 130.0,
      "13": 130.0,
      "14": 130.0,
      "15": 130.0,
      "16": 130.0,
      "17": 130.0,
      "18": 130.0,
      "19": 130.0,
      "20": 130.0,
      "21": 130.0,
      "22": 130.0,
      "23": 130.0,
      "24": 130.0,
      "1": 50.0,
      "2": 50.0,
      "3": 50.0,
      "4": 50.0,
      "5": 50.0,
      "6": 50.0
    }
  },
  {
    "id": 68,
    "angles": {
      "25": 51.4,
      "26": 51.4,
      "27": 51.4,
      "28": 51.4,
      "29": 51.4,
      "30": 51.4,
      "31": 51.4,
      "32": 51.4,
      "33": 51.4,
      "34": 51.4,
      "35": 51.4,
      "36": 51.4,
      "37": 51.4,
      "38": 51.4,
      "39": 51.4,
      "40": 51.4,
      "41": 51.4,
      "42": 51.4,
      "43": 51.4,
      "44": 51.4,
      "45": 51.4,
      "46": 51.4,
      "47": 51.4,
      "48": 51.4,
      "49": 51.4,
      "50": 51.4,
      "51": 51.4,
      "52": 51.4,
      "53": 51.4,
      "54": 51.4,
      "7": 128.6,
      "8": 128.6,
      "9": 128.6,
      "10": 128.6,
      "11": 128.6,
      "12": 128.6,
      "13": 128.6,
      "14": 128.6,
      "15": 128.6,
      "16": 128.6,
      "17": 128.6,
      "18": 128.6,
      "19": 128.6,
      "20": 128.6,
      "21": 128.6,
      "22": 128.6,
      "23": 128.6,
      "24": 128.6,
      "1": 51.4,
      "2": 51.4,
      "3": 51.4,
      "4": 51.4,
      "5": 51.4,
      "6": 51.4
    }
  },
  {
    "id": 69,
    "angles": {
      "25": 55.4,
      "26": 55.4,
      "27": 55.4,
      "28": 55.4,
      "29": 55.4,
      "30": 55.4,
      "31": 55.4,
      "32": 55.4,
      "33": 55.4,
      "34": 55.4,
      "35": 55.4,
      "36": 55.4,
      "37": 55.4,
      "38": 55.4,
      "39": 55.4,
      "40": 55.4,
      "41": 55.4,
      "42": 55.4,
      "43": 55.4,
      "44": 55.4,
      "45": 55.4,
      "46": 55.4,
      "47": 55.4,
      "48": 55.4,
      "49": 55.4,
      "50": 55.4,
      "51": 55.4,
      "52": 55.4,
      "53": 55.4,
      "54": 55.4,
      "7": 124.6,
      "8": 124.6,
      "9": 124.6,
      "10": 124.6,
      "11": 124.6,
      "12": 124.6,
      "13": 124.6,
      "14": 124.6,
      "15": 124.6,
      "16": 124.6,
      "17": 124.6,
      "18": 124.6,
      "19": 124.6,
      "20": 124.6,
      "21": 124.6,
      "22": 124.6,
      "23": 124.6,
      "24": 124.6,
      "1": 55.4,
      "2": 55.4,
      "3": 55.4,
      "4": 55.4,
      "5": 55.4,
      "6": 55.4
    }
  },
  {
    "id": 70,
    "angles": {
      "25": 61.7,
      "26": 61.7,
      "27": 61.7,
      "28": 61.7,
      "29": 61.7,
      "30": 61.7,
      "31": 61.7,
      "32": 61.7,
      "33": 61.7,
      "34": 61.7,
      "35": 61.7,
      "36": 61.7,
      "37": 61.7,
      "38": 61.7,
      "39": 61.7,
      "40": 61.7,
      "41": 61.7,
      "42": 61.7,
      "43": 61.7,
      "44": 61.7,
      "45": 61.7,
      "46": 61.7,
      "47": 61.7,
      "48": 61.7,
      "49": 61.7,
      "50": 61.7,
      "51": 61.7,
      "52": 61.7,
      "53": 61.7,
      "54": 61.7,
      "7": 118.3,
      "8": 118.3,
      "9": 118.3,
      "10": 118.3,
      "11": 118.3,
      "12": 118.3,
      "13": 118.3,
      "14": 118.3,
      "15": 118.3,
      "16": 118.3,
      "17": 118.3,
      "18": 118.3,
      "19": 118.3,
      "20": 118.3,
      "21": 118.3,
      "22": 118.3,
      "23": 118.3,
      "24": 118.3,
      "1": 61.7,
      "2": 61.7,
      "3": 61.7,
      "4": 61.7,
      "5": 61.7,
      "6": 61.7
    }
  },
  {
    "id": 71,
    "angles": {
      "25": 70.0,
      "26": 70.0,
      "27": 70.0,
      "28": 70.0,
      "29": 70.0,
      "30": 70.0,
      "31": 70.0,
      "32": 70.0,
      "33": 70.0,
      "34": 70.0,
      "35": 70.0,
      "36": 70.0,
      "37": 70.0,
      "38": 70.0,
      "39": 70.0,
      "40": 70.0,
      "41": 70.0,
      "42": 70.0,
      "43": 70.0,
      "44": 70.0,
      "45": 70.0,
      "46": 70.0,
      "47": 70.0,
      "48": 70.0,
      "49": 70.0,
      "50": 70.0,
      "51": 70.0,
      "52": 70.0,
      "53": 70.0,
      "54": 70.0,
      "7": 110.0,
      "8": 110.0,
      "9": 110.0,
      "10": 110.0,
      "11": 110.0,
      "12": 110.0,
      "13": 110.0,
      "14": 110.0,
      "15": 110.0,
      "16": 110.0,
      "17": 110.0,
      "18": 110.0,
      "19": 110.0,
      "20": 110.0,
      "21": 110.0,
      "22": 110.0,
      "23": 110.0,
      "24": 110.0,
      "1": 70.0,
      "2": 70.0,
      "3": 70.0,
      "4": 70.0,
      "5": 70.0,
      "6": 70.0
    }
  },
  {
    "id": 72,
    "angles": {
      "25": 79.6,
      "26": 79.6,
      "27": 79.6,
      "28": 79.6,
      "29": 79.6,
      "30": 79.6,
      "31": 79.6,
      "32": 79.6,
      "33": 79.6,
      "34": 79.6,
      "35": 79.6,
      "36": 79.6,
      "37": 79.6,
      "38": 79.6,
      "39": 79.6,
      "40": 79.6,
      "41": 79.6,
      "42": 79.6,
      "43": 79.6,
      "44": 79.6,
      "45": 79.6,
      "46": 79.6,
      "47": 79.6,
      "48": 79.6,
      "49": 79.6,
      "50": 79.6,
      "51": 79.6,
      "52": 79.6,
      "53": 79.6,
      "54": 79.6,
      "7": 100.4,
      "8": 100.4,
      "9": 100.4,
      "10": 100.4,
      "11": 100.4,
      "12": 100.4,
      "13": 100.4,
      "14": 100.4,
      "15": 100.4,
      "16": 100.4,
      "17": 100.4,
      "18": 100.4,
      "19": 100.4,
      "20": 100.4,
      "21": 100.4,
      "22": 100.4,
      "23": 100.4,
      "24": 100.4,
      "1": 79.6,
      "2": 79.6,
      "3": 79.6,
      "4": 79.6,
      "5": 79.6,
      "6": 79.6
    }
  },
  {
    "id": 73,
    "angles": {
      "25": 90.0,
      "26": 90.0,
      "27": 90.0,
      "28": 90.0,
      "29": 90.0,
      "30": 90.0,
      "31": 90.0,
      "32": 90.0,
      "33": 90.0,
      "34": 90.0,
      "35": 90.0,
      "36": 90.0,
      "37": 90.0,
      "38": 90.0,
      "39": 90.0,
      "40": 90.0,
      "41": 90.0,
      "42": 90.0,
      "43": 90.0,
      "44": 90.0,
      "45": 90.0,
      "46": 90.0,
      "47": 90.0,
      "48": 90.0,
      "49": 90.0,
      "50": 90.0,
      "51": 90.0,
      "52": 90.0,
      "53": 90.0,
      "54": 90.0,
      "7": 90.0,
      "8": 90.0,
      "9": 90.0,
      "10": 90.0,
      "11": 90.0,
      "12": 90.0,
      "13": 90.0,
      "14": 90.0,
      "15": 90.0,
      "16": 90.0,
      "17": 90.0,
      "18": 90.0,
      "19": 90.0,
      "20": 90.0,
      "21": 90.0,
      "22": 90.0,
      "23": 90.0,
      "24": 90.0,
      "1": 90.0,
      "2": 90.0,
      "3": 90.0,
      "4": 90.0,
      "5": 90.0,
      "6": 90.0
    }
  },
  {
    "id": 74,
    "angles": {
      "25": 100.4,
      "26": 100.4,
      "27": 100.4,
      "28": 100.4,
      "29": 100.4,
      "30": 100.4,
      "31": 100.4,
      "32": 100.4,
      "33": 100.4,
      "34": 100.4,
      "35": 100.4,
      "36": 100.4,
      "37": 100.4,
      "38": 100.4,
      "39": 100.4,
      "40": 100.4,
      "41": 100.4,
      "42": 100.4,
      "43": 100.4,
      "44": 100.4,
      "45": 100.4,
      "46": 100.4,
      "47": 100.4,
      "48": 100.4,
      "49": 100.4,
      "50": 100.4,
      "51": 100.4,
      "52": 100.4,
      "53": 100.4,
      "54": 100.4,
      "7": 79.6,
      "8": 79.6,
      "9": 79.6,
      "10": 79.6,
      "11": 79.6,
      "12": 79.6,
      "13": 79.6,
      "14": 79.6,
      "15": 79.6,
      "16": 79.6,
      "17": 79.6,
      "18": 79.6,
      "19": 79.6,
      "20": 79.6,
      "21": 79.6,
      "22": 79.6,
      "23": 79.6,
      "24": 79.6,
      "1": 100.4,
      "2": 100.4,
      "3": 100.4,
      "4": 100.4,
      "5": 100.4,
      "6": 100.4
    }
  },
  {
    "id": 75,
    "angles": {
      "25": 110.0,
      "26": 110.0,
      "27": 110.0,
      "28": 110.0,
      "29": 110.0,
      "30": 110.0,
      "31": 110.0,
      "32": 110.0,
      "33": 110.0,
      "34": 110.0,
      "35": 110.0,
      "36": 110.0,
      "37": 110.0,
      "38": 110.0,
      "39": 110.0,
      "40": 110.0,
      "41": 110.0,
      "42": 110.0,
      "43": 110.0,
      "44": 110.0,
      "45": 110.0,
      "46": 110.0,
      "47": 110.0,
      "48": 110.0,
      "49": 110.0,
      "50": 110.0,
      "51": 110.0,
      "52": 110.0,
      "53": 110.0,
      "54": 110.0,
      "7": 70.0,
      "8": 70.0,
      "9": 70.0,
      "10": 70.0,
      "11": 70.0,
      "12": 70.0,
      "13": 70.0,
      "14": 70.0,
      "15": 70.0,
      "16": 70.0,
      "17": 70.0,
      "18": 70.0,
      "19": 70.0,
      "20": 70.0,
      "21": 70.0,
      "22": 70.0,
      "23": 70.0,
      "24": 70.0,
      "1": 110.0,
      "2": 110.0,
      "3": 110.0,
      "4": 110.0,
      "5": 110.0,
      "6": 110.0
    }
  },
  {
    "id": 76,
    "angles": {
      "25": 118.3,
      "26": 118.3,
      "27": 118.3,
      "28": 118.3,
      "29": 118.3,
      "30": 118.3,
      "31": 118.3,
      "32": 118.3,
      "33": 118.3,
      "34": 118.3,
      "35": 118.3,
      "36": 118.3,
      "37": 118.3,
      "38": 118.3,
      "39": 118.3,
      "40": 118.3,
      "41": 118.3,
      "42": 118.3,
      "43": 118.3,
      "44": 118.3,
      "45": 118.3,
      "46": 118.3,
      "47": 118.3,
      "48": 118.3,
      "49": 118.3,
      "50": 118.3,
      "51": 118.3,
      "52": 118.3,
      "53": 118.3,
      "54": 118.3,
      "7": 61.7,
      "8": 61.7,
      "9": 61.7,
      "10": 61.7,
      "11": 61.7,
      "12": 61.7,
      "13": 61.7,
      "14": 61.7,
      "15": 61.7,
      "16": 61.7,
      "17": 61.7,
      "18": 61.7,
      "19": 61.7,
      "20": 61.7,
      "21": 61.7,
      "22": 61.7,
      "23": 61.7,
      "24": 61.7,
      "1": 118.3,
      "2": 118.3,
      "3": 118.3,
      "4": 118.3,
      "5": 118.3,
      "6": 118.3
    }
  },
  {
    "id": 77,
    "angles": {
      "25": 124.6,
      "26": 124.6,
      "27": 124.6,
      "28": 124.6,
      "29": 124.6,
      "30": 124.6,
      "31": 124.6,
      "32": 124.6,
      "33": 124.6,
      "34": 124.6,
      "35": 124.6,
      "36": 124.6,
      "37": 124.6,
      "38": 124.6,
      "39": 124.6,
      "40": 124.6,
      "41": 124.6,
      "42": 124.6,
      "43": 124.6,
      "44": 124.6,
      "45": 124.6,
      "46": 124.6,
      "47": 124.6,
      "48": 124.6,
      "49": 124.6,
      "50": 124.6,
      "51": 124.6,
      "52": 124.6,
      "53": 124.6,
      "54": 124.6,
      "7": 55.4,
      "8": 55.4,
      "9": 55.4,
      "10": 55.4,
      "11": 55.4,
      "12": 55.4,
      "13": 55.4,
      "14": 55.4,
      "15": 55.4,
      "16": 55.4,
      "17": 55.4,
      "18": 55.4,
      "19": 55.4,
      "20": 55.4,
      "21": 55.4,
      "22": 55.4,
      "23": 55.4,
      "24": 55.4,
      "1": 124.6,
      "2": 124.6,
      "3": 124.6,
      "4": 124.6,
      "5": 124.6,
      "6": 124.6
    }
  },
  {
    "id": 78,
    "angles": {
      "25": 128.6,
      "26": 128.6,
      "27": 128.6,
      "28": 128.6,
      "29": 128.6,
      "30": 128.6,
      "31": 128.6,
      "32": 128.6,
      "33": 128.6,
      "34": 128.6,
      "35": 128.6,
      "36": 128.6,
      "37": 128.6,
      "38": 128.6,
      "39": 128.6,
      "40": 128.6,
      "41": 128.6,
      "42": 128.6,
      "43": 128.6,
      "44": 128.6,
      "45": 128.6,
      "46": 128.6,
      "47": 128.6,
      "48": 128.6,
      "49": 128.6,
      "50": 128.6,
      "51": 128.6,
      "52": 128.6,
      "53": 128.6,
      "54": 128.6,
      "7": 51.4,
      "8": 51.4,
      "9": 51.4,
      "10": 51.4,
      "11": 51.4,
      "12": 51.4,
      "13": 51.4,
      "14": 51.4,
      "15": 51.4,
      "16": 51.4,
      "17": 51.4,
      "18": 51.4,
      "19": 51.4,
      "20": 51.4,
      "21": 51.4,
      "22": 51.4,
      "23": 51.4,
      "24": 51.4,
      "1": 128.6,
      "2": 128.6,
      "3": 128.6,
      "4": 128.6,
      "5": 128.6,
      "6": 128.6
    }
  },
  {
    "id": 79,
    "angles": {
      "25": 130.0,
      "26": 130.0,
      "27": 130.0,
      "28": 130.0,
      "29": 130.0,
      "30": 130.0,
      "31": 130.0,
      "32": 130.0,
      "33": 130.0,
      "34": 130.0,
      "35": 130.0,
      "36": 130.0,
      "37": 130.0,
      "38": 130.0,
      "39": 130.0,
      "40": 130.0,
      "41": 130.0,
      "42": 130.0,
      "43": 130.0,
      "44": 130.0,
      "45": 130.0,
      "46": 130.0,
      "47": 130.0,
      "48": 130.0,
      "49": 130.0,
      "50": 130.0,
      "51": 130.0,
      "52": 130.0,
      "53": 130.0,
      "54": 130.0,
      "7": 50.0,
      "8": 50.0,
      "9": 50.0,
      "10": 50.0,
      "11": 50.0,
      "12": 50.0,
      "13": 50.0,
      "14": 50.0,
      "15": 50.0,
      "16": 50.0,
      "17": 50.0,
      "18": 50.0,
      "19": 50.0,
      "20": 50.0,
      "21": 50.0,
      "22": 50.0,
      "23": 50.0,
      "24": 50.0,
      "1": 130.0,
      "2": 130.0,
      "3": 130.0,
      "4": 130.0,
      "5": 130.0,
      "6": 130.0
    }
  },
  {
    "id": 80,
    "angles": {
      "25": 128.6,
      "26": 128.6,
      "27": 128.6,
      "28": 128.6,
      "29": 128.6,
      "30": 128.6,
      "31": 128.6,
      "32": 128.6,
      "33": 128.6,
      "34": 128.6,
      "35": 128.6,
      "36": 128.6,
      "37": 128.6,
      "38": 128.6,
      "39": 128.6,
      "40": 128.6,
      "41": 128.6,
      "42": 128.6,
      "43": 128.6,
      "44": 128.6,
      "45": 128.6,
      "46": 128.6,
      "47": 128.6,
      "48": 128.6,
      "49": 128.6,
      "50": 128.6,
      "51": 128.6,
      "52": 128.6,
      "53": 128.6,
      "54": 128.6,
      "7": 51.4,
      "8": 51.4,
      "9": 51.4,
      "10": 51.4,
      "11": 51.4,
      "12": 51.4,
      "13": 51.4,
      "14": 51.4,
      "15": 51.4,
      "16": 51.4,
      "17": 51.4,
      "18": 51.4,
      "19": 51.4,
      "20": 51.4,
      "21": 51.4,
      "22": 51.4,
      "23": 51.4,
      "24": 51.4,
      "1": 128.6,
      "2": 128.6,
      "3": 128.6,
      "4": 128.6,
      "5": 128.6,
      "6": 128.6
    }
  },
  {
    "id": 81,
    "angles": {
      "25": 124.6,
      "26": 124.6,
      "27": 124.6,
      "28": 124.6,
      "29": 124.6,
      "30": 124.6,
      "31": 124.6,
      "32": 124.6,
      "33": 124.6,
      "34": 124.6,
      "35": 124.6,
      "36": 124.6,
      "37": 124.6,
      "38": 124.6,
      "39": 124.6,
      "40": 124.6,
      "41": 124.6,
      "42": 124.6,
      "43": 124.6,
      "44": 124.6,
      "45": 124.6,
      "46": 124.6,
      "47": 124.6,
      "48": 124.6,
      "49": 124.6,
      "50": 124.6,
      "51": 124.6,
      "52": 124.6,
      "53": 124.6,
      "54": 124.6,
      "7": 55.4,
      "8": 55.4,
      "9": 55.4,
      "10": 55.4,
      "11": 55.4,
      "12": 55.4,
      "13": 55.4,
      "14": 55.4,
      "15": 55.4,
      "16": 55.4,
      "17": 55.4,
      "18": 55.4,
      "19": 55.4,
      "20": 55.4,
      "21": 55.4,
      "22": 55.4,
      "23": 55.4,
      "24": 55.4,
      "1": 124.6,
      "2": 124.6,
      "3": 124.6,
      "4": 124.6,
      "5": 124.6,
      "6": 124.6
    }
  },
  {
    "id": 82,
    "angles": {
      "25": 118.3,
      "26": 118.3,
      "27": 118.3,
      "28": 118.3,
      "29": 118.3,
      "30": 118.3,
      "31": 118.3,
      "32": 118.3,
      "33": 118.3,
      "34": 118.3,
      "35": 118.3,
      "36": 118.3,
      "37": 118.3,
      "38": 118.3,
      "39": 118.3,
      "40": 118.3,
      "41": 118.3,
      "42": 118.3,
      "43": 118.3,
      "44": 118.3,
      "45": 118.3,
      "46": 118.3,
      "47": 118.3,
      "48": 118.3,
      "49": 118.3,
      "50": 118.3,
      "51": 118.3,
      "52": 118.3,
      "53": 118.3,
      "54": 118.3,
      "7": 61.7,
      "8": 61.7,
      "9": 61.7,
      "10": 61.7,
      "11": 61.7,
      "12": 61.7,
      "13": 61.7,
      "14": 61.7,
      "15": 61.7,
      "16": 61.7,
      "17": 61.7,
      "18": 61.7,
      "19": 61.7,
      "20": 61.7,
      "21": 61.7,
      "22": 61.7,
      "23": 61.7,
      "24": 61.7,
      "1": 118.3,
      "2": 118.3,
      "3": 118.3,
      "4": 118.3,
      "5": 118.3,
      "6": 118.3
    }
  },
  {
    "id": 83,
    "angles": {
      "25": 110.0,
      "26": 110.0,
      "27": 110.0,
      "28": 110.0,
      "29": 110.0,
      "30": 110.0,
      "31": 110.0,
      "32": 110.0,
      "33": 110.0,
      "34": 110.0,
      "35": 110.0,
      "36": 110.0,
      "37": 110.0,
      "38": 110.0,
      "39": 110.0,
      "40": 110.0,
      "41": 110.0,
      "42": 110.0,
      "43": 110.0,
      "44": 110.0,
      "45": 110.0,
      "46": 110.0,
      "47": 110.0,
      "48": 110.0,
      "49": 110.0,
      "50": 110.0,
      "51": 110.0,
      "52": 110.0,
      "53": 110.0,
      "54": 110.0,
      "7": 70.0,
      "8": 70.0,
      "9": 70.0,
      "10": 70.0,
      "11": 70.0,
      "12": 70.0,
      "13": 70.0,
      "14": 70.0,
      "15": 70.0,
      "16": 70.0,
      "17": 70.0,
      "18": 70.0,
      "19": 70.0,
      "20": 70.0,
      "21": 70.0,
      "22": 70.0,
      "23": 70.0,
      "24": 70.0,
      "1": 110.0,
      "2": 110.0,
      "3": 110.0,
      "4": 110.0,
      "5": 110.0,
      "6": 110.0
    }
  },
  {
    "id": 84,
    "angles": {
      "25": 100.4,
      "26": 100.4,
      "27": 100.4,
      "28": 100.4,
      "29": 100.4,
      "30": 100.4,
      "31": 100.4,
      "32": 100.4,
      "33": 100.4,
      "34": 100.4,
      "35": 100.4,
      "36": 100.4,
      "37": 100.4,
      "38": 100.4,
      "39": 100.4,
      "40": 100.4,
      "41": 100.4,
      "42": 100.4,
      "43": 100.4,
      "44": 100.4,
      "45": 100.4,
      "46": 100.4,
      "47": 100.4,
      "48": 100.4,
      "49": 100.4,
      "50": 100.4,
      "51": 100.4,
      "52": 100.4,
      "53": 100.4,
      "54": 100.4,
      "7": 79.6,
      "8": 79.6,
      "9": 79.6,
      "10": 79.6,
      "11": 79.6,
      "12": 79.6,
      "13": 79.6,
      "14": 79.6,
      "15": 79.6,
      "16": 79.6,
      "17": 79.6,
      "18": 79.6,
      "19": 79.6,
      "20": 79.6,
      "21": 79.6,
      "22": 79.6,
      "23": 79.6,
      "24": 79.6,
      "1": 100.4,
      "2": 100.4,
      "3": 100.4,
      "4": 100.4,
      "5": 100.4,
      "6": 100.4
    }
  },
  {
    "id": 85,
    "angles": {
      "25": 90.0,
      "26": 90.0,
      "27": 90.0,
      "28": 90.0,
      "29": 90.0,
      "30": 90.0,
      "31": 90.0,
      "32": 90.0,
      "33": 90.0,
      "34": 90.0,
      "35": 90.0,
      "36": 90.0,
      "37": 90.0,
      "38": 90.0,
      "39": 90.0,
      "40": 90.0,
      "41": 90.0,
      "42": 90.0,
      "43": 90.0,
      "44": 90.0,
      "45": 90.0,
      "46": 90.0,
      "47": 90.0,
      "48": 90.0,
      "49": 90.0,
      "50": 90.0,
      "51": 90.0,
      "52": 90.0,
      "53": 90.0,
      "54": 90.0,
      "7": 90.0,
      "8": 90.0,
      "9": 90.0,
      "10": 90.0,
      "11": 90.0,
      "12": 90.0,
      "13": 90.0,
      "14": 90.0,
      "15": 90.0,
      "16": 90.0,
      "17": 90.0,
      "18": 90.0,
      "19": 90.0,
      "20": 90.0,
      "21": 90.0,
      "22": 90.0,
      "23": 90.0,
      "24": 90.0,
      "1": 90.0,
      "2": 90.0,
      "3": 90.0,
      "4": 90.0,
      "5": 90.0,
      "6": 90.0
    }
  },
  {
    "id": 86,
    "angles": {
      "25": 79.6,
      "26": 79.6,
      "27": 79.6,
      "28": 79.6,
      "29": 79.6,
      "30": 79.6,
      "31": 79.6,
      "32": 79.6,
      "33": 79.6,
      "34": 79.6,
      "35": 79.6,
      "36": 79.6,
      "37": 79.6,
      "38": 79.6,
      "39": 79.6,
      "40": 79.6,
      "41": 79.6,
      "42": 79.6,
      "43": 79.6,
      "44": 79.6,
      "45": 79.6,
      "46": 79.6,
      "47": 79.6,
      "48": 79.6,
      "49": 79.6,
      "50": 79.6,
      "51": 79.6,
      "52": 79.6,
      "53": 79.6,
      "54": 79.6,
      "7": 100.4,
      "8": 100.4,
      "9": 100.4,
      "10": 100.4,
      "11": 100.4,
      "12": 100.4,
      "13": 100.4,
      "14": 100.4,
      "15": 100.4,
      "16": 100.4,
      "17": 100.4,
      "18": 100.4,
      "19": 100.4,
      "20": 100.4,
      "21": 100.4,
      "22": 100.4,
      "23": 100.4,
      "24": 100.4,
      "1": 79.6,
      "2": 79.6,
      "3": 79.6,
      "4": 79.6,
      "5": 79.6,
      "6": 79.6
    }
  },
  {
    "id": 87,
    "angles": {
      "25": 70.0,
      "26": 70.0,
      "27": 70.0,
      "28": 70.0,
      "29": 70.0,
      "30": 70.0,
      "31": 70.0,
      "32": 70.0,
      "33": 70.0,
      "34": 70.0,
      "35": 70.0,
      "36": 70.0,
      "37": 70.0,
      "38": 70.0,
      "39": 70.0,
      "40": 70.0,
      "41": 70.0,
      "42": 70.0,
      "43": 70.0,
      "44": 70.0,
      "45": 70.0,
      "46": 70.0,
      "47": 70.0,
      "48": 70.0,
      "49": 70.0,
      "50": 70.0,
      "51": 70.0,
      "52": 70.0,
      "53": 70.0,
      "54": 70.0,
      "7": 110.0,
      "8": 110.0,
      "9": 110.0,
      "10": 110.0,
      "11": 110.0,
      "12": 110.0,
      "13": 110.0,
      "14": 110.0,
      "15": 110.0,
      "16": 110.0,
      "17": 110.0,
      "18": 110.0,
      "19": 110.0,
      "20": 110.0,
      "21": 110.0,
      "22": 110.0,
      "23": 110.0,
      "24": 110.0,
      "1": 70.0,
      "2": 70.0,
      "3": 70.0,
      "4": 70.0,
      "5": 70.0,
      "6": 70.0
    }
  },
  {
    "id": 88,
    "angles": {
      "25": 61.7,
      "26": 61.7,
      "27": 61.7,
      "28": 61.7,
      "29": 61.7,
      "30": 61.7,
      "31": 61.7,
      "32": 61.7,
      "33": 61.7,
      "34": 61.7,
      "35": 61.7,
      "36": 61.7,
      "37": 61.7,
      "38": 61.7,
      "39": 61.7,
      "40": 61.7,
      "41": 61.7,
      "42": 61.7,
      "43": 61.7,
      "44": 61.7,
      "45": 61.7,
      "46": 61.7,
      "47": 61.7,
      "48": 61.7,
      "49": 61.7,
      "50": 61.7,
      "51": 61.7,
      "52": 61.7,
      "53": 61.7,
      "54": 61.7,
      "7": 118.3,
      "8": 118.3,
      "9": 118.3,
      "10": 118.3,
      "11": 118.3,
      "12": 118.3,
      "13": 118.3,
      "14": 118.3,
      "15": 118.3,
      "16": 118.3,
      "17": 118.3,
      "18": 118.3,
      "19": 118.3,
      "20": 118.3,
      "21": 118.3,
      "22": 118.3,
      "23": 118.3,
      "24": 118.3,
      "1": 61.7,
      "2": 61.7,
      "3": 61.7,
      "4": 61.7,
      "5": 61.7,
      "6": 61.7
    }
  },
  {
    "id": 89,
    "angles": {
      "25": 55.4,
      "26": 55.4,
      "27": 55.4,
      "28": 55.4,
      "29": 55.4,
      "30": 55.4,
      "31": 55.4,
      "32": 55.4,
      "33": 55.4,
      "34": 55.4,
      "35": 55.4,
      "36": 55.4,
      "37": 55.4,
      "38": 55.4,
      "39": 55.4,
      "40": 55.4,
      "41": 55.4,
      "42": 55.4,
      "43": 55.4,
      "44": 55.4,
      "45": 55.4,
      "46": 55.4,
      "47": 55.4,
      "48": 55.4,
      "49": 55.4,
      "50": 55.4,
      "51": 55.4,
      "52": 55.4,
      "53": 55.4,
      "54": 55.4,
      "7": 124.6,
      "8": 124.6,
      "9": 124.6,
      "10": 124.6,
      "11": 124.6,
      "12": 124.6,
      "13": 124.6,
      "14": 124.6,
      "15": 124.6,
      "16": 124.6,
      "17": 124.6,
      "18": 124.6,
      "19": 124.6,
      "20": 124.6,
      "21": 124.6,
      "22": 124.6,
      "23": 124.6,
      "24": 124.6,
      "1": 55.4,
      "2": 55.4,
      "3": 55.4,
      "4": 55.4,
      "5": 55.4,
      "6": 55.4
    }
  },
  {
    "id": 90,
    "angles": {
      "25": 51.4,
      "26": 51.4,
      "27": 51.4,
      "28": 51.4,
      "29": 51.4,
      "30": 51.4,
      "31": 51.4,
      "32": 51.4,
      "33": 51.4,
      "34": 51.4,
      "35": 51.4,
      "36": 51.4,
      "37": 51.4,
      "38": 51.4,
      "39": 51.4,
      "40": 51.4,
      "41": 51.4,
      "42": 51.4,
      "43": 51.4,
      "44": 51.4,
      "45": 51.4,
      "46": 51.4,
      "47": 51.4,
      "48": 51.4,
      "49": 51.4,
      "50": 51.4,
      "51": 51.4,
      "52": 51.4,
      "53": 51.4,
      "54": 51.4,
      "7": 128.6,
      "8": 128.6,
      "9": 128.6,
      "10": 128.6,
      "11": 128.6,
      "12": 128.6,
      "13": 128.6,
      "14": 128.6,
      "15": 128.6,
      "16": 128.6,
      "17": 128.6,
      "18": 128.6,
      "19": 128.6,
      "20": 128.6,
      "21": 128.6,
      "22": 128.6,
      "23": 128.6,
      "24": 128.6,
      "1": 51.4,
      "2": 51.4,
      "3": 51.4,
      "4": 51.4,
      "5": 51.4,
      "6": 51.4
    }
  },
  {
    "id": 91,
    "angles": {
      "25": 50.0,
      "26": 50.0,
      "27": 50.0,
      "28": 50.0,
      "29": 50.0,
      "30": 50.0,
      "31": 50.0,
      "32": 50.0,
      "33": 50.0,
      "34": 50.0,
      "35": 50.0,
      "36": 50.0,
      "37": 50.0,
      "38": 50.0,
      "39": 50.0,
      "40": 50.0,
      "41": 50.0,
      "42": 50.0,
      "43": 50.0,
      "44": 50.0,
      "45": 50.0,
      "46": 50.0,
      "47": 50.0,
      "48": 50.0,
      "49": 50.0,
      "50": 50.0,
      "51": 50.0,
      "52": 50.0,
      "53": 50.0,
      "54": 50.0,
      "7": 130.0,
      "8": 130.0,
      "9": 130.0,
      "10": 130.0,
      "11": 130.0,
      "12": 130.0,
      "13": 130.0,
      "14": 130.0,
      "15": 130.0,
      "16": 130.0,
      "17": 130.0,
      "18": 130.0,
      "19": 130.0,
      "20": 130.0,
      "21": 130.0,
      "22": 130.0,
      "23": 130.0,
      "24": 130.0,
      "1": 50.0,
      "2": 50.0,
      "3": 50.0,
      "4": 50.0,
      "5": 50.0,
      "6": 50.0
    }
  },
  {
    "id": 92,
    "angles": {
      "25": 51.4,
      "26": 51.4,
      "27": 51.4,
      "28": 51.4,
      "29": 51.4,
      "30": 51.4,
      "31": 51.4,
      "32": 51.4,
      "33": 51.4,
      "34": 51.4,
      "35": 51.4,
      "36": 51.4,
      "37": 51.4,
      "38": 51.4,
      "39": 51.4,
      "40": 51.4,
      "41": 51.4,
      "42": 51.4,
      "43": 51.4,
      "44": 51.4,
      "45": 51.4,
      "46": 51.4,
      "47": 51.4,
      "48": 51.4,
      "49": 51.4,
      "50": 51.4,
      "51": 51.4,
      "52": 51.4,
      "53": 51.4,
      "54": 51.4,
      "7": 128.6,
      "8": 128.6,
      "9": 128.6,
      "10": 128.6,
      "11": 128.6,
      "12": 128.6,
      "13": 128.6,
      "14": 128.6,
      "15": 128.6,
      "16": 128.6,
      "17": 128.6,
      "18": 128.6,
      "19": 128.6,
      "20": 128.6,
      "21": 128.6,
      "22": 128.6,
      "23": 128.6,
      "24": 128.6,
      "1": 51.4,
      "2": 51.4,
      "3": 51.4,
      "4": 51.4,
      "5": 51.4,
      "6": 51.4
    }
  },
  {
    "id": 93,
    "angles": {
      "25": 55.4,
      "26": 55.4,
      "27": 55.4,
      "28": 55.4,
      "29": 55.4,
      "30": 55.4,
      "31": 55.4,
      "32": 55.4,
      "33": 55.4,
      "34": 55.4,
      "35": 55.4,
      "36": 55.4,
      "37": 55.4,
      "38": 55.4,
      "39": 55.4,
      "40": 55.4,
      "41": 55.4,
      "42": 55.4,
      "43": 55.4,
      "44": 55.4,
      "45": 55.4,
      "46": 55.4,
      "47": 55.4,
      "48": 55.4,
      "49": 55.4,
      "50": 55.4,
      "51": 55.4,
      "52": 55.4,
      "53": 55.4,
      "54": 55.4,
      "7": 124.6,
      "8": 124.6,
      "9": 124.6,
      "10": 124.6,
      "11": 124.6,
      "12": 124.6,
      "13": 124.6,
      "14": 124.6,
      "15": 124.6,
      "16": 124.6,
      "17": 124.6,
      "18": 124.6,
      "19": 124.6,
      "20": 124.6,
      "21": 124.6,
      "22": 124.6,
      "23": 124.6,
      "24": 124.6,
      "1": 55.4,
      "2": 55.4,
      "3": 55.4,
      "4": 55.4,
      "5": 55.4,
      "6": 55.4
    }
  },
  {
    "id": 94,
    "angles": {
      "25": 61.7,
      "26": 61.7,
      "27": 61.7,
      "28": 61.7,
      "29": 61.7,
      "30": 61.7,
      "31": 61.7,
      "32": 61.7,
      "33": 61.7,
      "34": 61.7,
      "35": 61.7,
      "36": 61.7,
      "37": 61.7,
      "38": 61.7,
      "39": 61.7,
      "40": 61.7,
      "41": 61.7,
      "42": 61.7,
      "43": 61.7,
      "44": 61.7,
      "45": 61.7,
      "46": 61.7,
      "47": 61.7,
      "48": 61.7,
      "49": 61.7,
      "50": 61.7,
      "51": 61.7,
      "52": 61.7,
      "53": 61.7,
      "54": 61.7,
      "7": 118.3,
      "8": 118.3,
      "9": 118.3,
      "10": 118.3,
      "11": 118.3,
      "12": 118.3,
      "13": 118.3,
      "14": 118.3,
      "15": 118.3,
      "16": 118.3,
      "17": 118.3,
      "18": 118.3,
      "19": 118.3,
      "20": 118.3,
      "21": 118.3,
      "22": 118.3,
      "23": 118.3,
      "24": 118.3,
      "1": 61.7,
      "2": 61.7,
      "3": 61.7,
      "4": 61.7,
      "5": 61.7,
      "6": 61.7
    }
  },
  {
    "id": 95,
    "angles": {
      "25": 70.0,
      "26": 70.0,
      "27": 70.0,
      "28": 70.0,
      "29": 70.0,
      "30": 70.0,
      "31": 70.0,
      "32": 70.0,
      "33": 70.0,
      "34": 70.0,
      "35": 70.0,
      "36": 70.0,
      "37": 70.0,
      "38": 70.0,
      "39": 70.0,
      "40": 70.0,
      "41": 70.0,
      "42": 70.0,
      "43": 70.0,
      "44": 70.0,
      "45": 70.0,
      "46": 70.0,
      "47": 70.0,
      "48": 70.0,
      "49": 70.0,
      "50": 70.0,
      "51": 70.0,
      "52": 70.0,
      "53": 70.0,
      "54": 70.0,
      "7": 110.0,
      "8": 110.0,
      "9": 110.0,
      "10": 110.0,
      "11": 110.0,
      "12": 110.0,
      "13": 110.0,
      "14": 110.0,
      "15": 110.0,
      "16": 110.0,
      "17": 110.0,
      "18": 110.0,
      "19": 110.0,
      "20": 110.0,
      "21": 110.0,
      "22": 110.0,
      "23": 110.0,
      "24": 110.0,
      "1": 70.0,
      "2": 70.0,
      "3": 70.0,
      "4": 70.0,
      "5": 70.0,
      "6": 70.0
    }
  },
  {
    "id": 96,
    "angles": {
      "25": 79.6,
      "26": 79.6,
      "27": 79.6,
      "28": 79.6,
      "29": 79.6,
      "30": 79.6,
      "31": 79.6,
      "32": 79.6,
      "33": 79.6,
      "34": 79.6,
      "35": 79.6,
      "36": 79.6,
      "37": 79.6,
      "38": 79.6,
      "39": 79.6,
      "40": 79.6,
      "41": 79.6,
      "42": 79.6,
      "43": 79.6,
      "44": 79.6,
      "45": 79.6,
      "46": 79.6,
      "47": 79.6,
      "48": 79.6,
      "49": 79.6,
      "50": 79.6,
      "51": 79.6,
      "52": 79.6,
      "53": 79.6,
      "54": 79.6,
      "7": 100.4,
      "8": 100.4,
      "9": 100.4,
      "10": 100.4,
      "11": 100.4,
      "12": 100.4,
      "13": 100.4,
      "14": 100.4,
      "15": 100.4,
      "16": 100.4,
      "17": 100.4,
      "18": 100.4,
      "19": 100.4,
      "20": 100.4,
      "21": 100.4,
      "22": 100.4,
      "23": 100.4,
      "24": 100.4,
      "1": 79.6,
      "2": 79.6,
      "3": 79.6,
      "4": 79.6,
      "5": 79.6,
      "6": 79.6
    }
  },
  {
    "id": 97,
    "angles": {
      "1": 90,
      "2": 90,
      "3": 90,
      "4": 90,
      "5": 90,
      "6": 90,
      "7": 90,
      "8": 90,
      "9": 90,
      "10": 90,
      "11": 90,
      "12": 90,
      "13": 90,
      "14": 90,
      "15": 90,
      "16": 90,
      "17": 90,
      "18": 90,
      "19": 90,
      "20": 90,
      "21": 90,
      "22": 90,
      "23": 90,
      "24": 90,
      "25": 90,
      "26": 90,
      "27": 90,
      "28": 90,
      "29": 90,
      "30": 90,
      "31": 90,
      "32": 90,
      "33": 90,
      "34": 90,
      "35": 90,
      "36": 90,
      "37": 90,
      "38": 90,
      "39": 90,
      "40": 90,
      "41": 90,
      "42": 90,
      "43": 90,
      "44": 90,
      "45": 90,
      "46": 90,
      "47": 90,
      "48": 90,
      "49": 90,
      "50": 90,
      "51": 90,
      "52": 90,
      "53": 90,
      "54": 90
    }
  }
]